{
  "贵州五谷丰粮油储备有限责任公司": 1769,
  "尚品缘自助烧烤(装修中)": 768,
  "贵州向成汽车": 482,
  "中国工商银行(清镇东门桥支行)": 534,
  "中共清镇市公安局城东派出所支部委员会": 446,
  "老匠人艺术建材有限公司": 466,
  "王记餐馆": 2705,
  "贵州聚乾商品混凝土有限公司": 598,
  "回龙寺互通": 534,
  "北师大老教授协会实验幼儿园": 406,
  "金华派出所蒿芝警务室": 410,
  "蒿芝居委会": 504,
  "042村道": 462,
  "京东电子商务产业园区(南门)": 1149,
  "邓坡": 719,
  "贵西能源金清加油站": 641,
  "金华镇中心卫生院门急诊楼": 422,
  "金阳客车站(出站口)": 442,
  "商城西路": 499,
  "苗家砂锅酸辣烫": 449,
  "iu酒店(贵阳西南商贸城金阳客运站店)": 422,
  "金源社区小箐村微型消防站": 483,
  "贵州鑫元电力建设工程有限公司": 823,
  "云潭南路(南)(快速公交站)": 1010,
  "金阳南路": 594,
  "锦秀钰人健康管理中心": 404,
  "世纪金源购物中心A座乐尚生活馆(世纪金源购物中心店)": 753,
  "珍珠泉街": 422,
  "好医生贵州运营中心": 408,
  "贵阳世纪城龙城庄园": 597,
  "小背篓野生菌煲鹅汤(世纪城店)": 481
}