{
  "up": {
    "烘焙奶茶设备": 1,
    "冉林禾土黄牛肉粉总店": 2,
    "下茶园": 3,
    "悠唐家居定制(世纪金源购物中心店)": 4,
    "贵阳农商银行(观山湖支行)": 5,
    "卓雅舞蹈": 6,
    "观山湖区第二十五幼儿园": 7,
    "碧桂园·十里晴川(建设中)": 8,
    "精品带皮牛肉粉(贵阳二铺总店)": 9,
    "交通大数据研发中心": 10,
    "北京西路": 11,
    "金阳客车站": 12,
    "金华派出所干井村委会警务助理工作站": 13,
    "黄土坡": 14,
    "贝贝幼儿园": 15,
    "贵阳朗升汽车服务有限公司": 16,
    "京东亚洲一号贵阳观山湖物流园(北1门)": 17,
    "贵州泰歌凌机械化有限公司": 18,
    "广大城·耀晟一期": 19,
    "金华派出所蒿芝村委会警务助理工作站": 20,
    "回龙寺互通": 21,
    "精校传动轴": 22,
    "下铺村": 23,
    "碧桂园·茶马古镇停车场": 24,
    "百马大道": 25,
    "贵黄高速": 26,
    "赞吧啦海鲜自助烧烤": 27,
    "安稳汽修厂": 28,
    "贵阳·上汽荣威贵州赛尔旗舰店": 29,
    "普洛斯贵阳铁路港物流园": 30,
    "清镇市物流新城幼儿园": 31,
    "奥林温泉接待中心": 32,
    "兰花坡": 33,
    "敖记老贵阳肠旺面(置悦城·贵安馨苑店)": 34
  },
  "down": {
    "敖记老贵阳肠旺面(置悦城·贵安馨苑店)": 35,
    "兰花坡": 36,
    "奥林温泉接待中心": 37,
    "清镇市物流新城幼儿园": 38,
    "普洛斯贵阳铁路港物流园": 39,
    "贵阳·上汽荣威贵州赛尔旗舰店": 40,
    "安稳汽修厂": 41,
    "赞吧啦海鲜自助烧烤": 42,
    "贵黄高速": 43,
    "百马大道": 44,
    "碧桂园·茶马古镇停车场": 45,
    "下铺村": 46,
    "精校传动轴": 47,
    "回龙寺互通": 48,
    "金华派出所蒿芝村委会警务助理工作站": 49,
    "广大城·耀晟一期": 50,
    "贵州泰歌凌机械化有限公司": 51,
    "京东亚洲一号贵阳观山湖物流园(北1门)": 52,
    "贵阳朗升汽车服务有限公司": 53,
    "贝贝幼儿园": 54,
    "黄土坡": 55,
    "金华派出所干井村委会警务助理工作站": 56,
    "金阳客车站": 57,
    "北京西路": 58,
    "交通大数据研发中心": 59,
    "精品带皮牛肉粉(贵阳二铺总店)": 60,
    "碧桂园·十里晴川(建设中)": 61,
    "观山湖区第二十五幼儿园": 62,
    "卓雅舞蹈": 63,
    "贵阳农商银行(观山湖支行)": 64,
    "悠唐家居定制(世纪金源购物中心店)": 65,
    "下茶园": 66,
    "冉林禾土黄牛肉粉总店": 67,
    "烘焙奶茶设备": 68
  }
}