{
  "up": {
    "1": "中澳国际商务港(建设中)",
    "2": "贵州名鉴司法鉴定中心",
    "3": "贵阳九岸酒店",
    "4": "K1隐食(贵阳北站店)",
    "5": "恒8连锁酒店(贵阳北站店)",
    "6": "汇北缘宾馆",
    "7": "大关村",
    "8": "财静留一手烤鱼《小豆腐坨坨肉》分店",
    "9": "香瑞楼全牛羊火锅店",
    "10": "北二环入口(西向)",
    "11": "北二环",
    "12": "都拉营出口(北二环东向)",
    "13": "招呼站(公交站)",
    "14": "北二环入口(东南向)",
    "15": "北二环出口(东向)",
    "16": "吾乡二号隧道",
    "17": "贵山陵园",
    "18": "罗三姐小菜馆",
    "19": "万顿子美术教育",
    "20": "北京东路",
    "21": "云保大道",
    "22": "东盟营造公司",
    "23": "贵州工大土木工程试验检测股份有限公司",
    "24": "贵州砼柴商品混凝土有限公司",
    "25": "国药控股贵州医药有限公司",
    "26": "迈达盛能源加油站(高穴二号站)",
    "27": "小张牛肉粉面馆",
    "28": "三江桥",
    "29": "水田三江九年制学校",
    "30": "129县道",
    "31": "田坝头",
    "32": "桥边"
  },
  "down": {
    "33": "桥边",
    "34": "田坝头",
    "35": "129县道",
    "36": "水田三江九年制学校",
    "37": "三江桥",
    "38": "小张牛肉粉面馆",
    "39": "迈达盛能源加油站(高穴二号站)",
    "40": "国药控股贵州医药有限公司",
    "41": "贵州砼柴商品混凝土有限公司",
    "42": "贵州工大土木工程试验检测股份有限公司",
    "43": "东盟营造公司",
    "44": "云保大道",
    "45": "北京东路",
    "46": "万顿子美术教育",
    "47": "罗三姐小菜馆",
    "48": "贵山陵园",
    "49": "吾乡二号隧道",
    "50": "北二环出口(东向)",
    "51": "北二环入口(东南向)",
    "52": "招呼站(公交站)",
    "53": "都拉营出口(北二环东向)",
    "54": "北二环",
    "55": "北二环入口(西向)",
    "56": "香瑞楼全牛羊火锅店",
    "57": "财静留一手烤鱼《小豆腐坨坨肉》分店",
    "58": "大关村",
    "59": "汇北缘宾馆",
    "60": "恒8连锁酒店(贵阳北站店)",
    "61": "K1隐食(贵阳北站店)",
    "62": "贵阳九岸酒店",
    "63": "贵州名鉴司法鉴定中心",
    "64": "中澳国际商务港(建设中)"
  }
}