{
  "up": {
    "北京西路": 1,
    "百花大道地铁站D口": 2,
    "金关社区贵轮居委会": 3,
    "新建汽制厂幼儿园": 4,
    "飞来山": 5,
    "后坝派出所": 6,
    "秘招专治颈椎": 7,
    "贵阳市南明区苗苗实验学校": 8,
    "土黄牛肉馆(2店)": 9,
    "应腾达科目二考场": 10,
    "龙云雕刻石材有限公司贵州办事处": 11,
    "梯田湿地": 12,
    "贵阳阿哈湖国家湿地公园-廊桥烟溪": 13,
    "133县道": 14,
    "贵阳市林城苗苗小学": 15,
    "贵州省农业科学院": 16,
    "金竹派出所贵州省农科院附中执勤点": 17,
    "贵州东方驾校科目二训练场": 18,
    "徐记小吃素粉": 19,
    "大理石": 20,
    "贵安大道辅路": 21,
    "贵安大道": 22,
    "康打路": 23,
    "小张自采草莓园": 24,
    "隆昌村村委会": 25,
    "隆昌坡": 26,
    "天河潭派出所停车场治安办": 27,
    "摆顶": 28,
    "贵州文煜贸易有限公司": 29,
    "中铁十七局集团": 30
  },
  "down": {
    "中铁十七局集团": 31,
    "贵州文煜贸易有限公司": 32,
    "摆顶": 33,
    "天河潭派出所停车场治安办": 34,
    "隆昌坡": 35,
    "隆昌村村委会": 36,
    "小张自采草莓园": 37,
    "康打路": 38,
    "贵安大道": 39,
    "贵安大道辅路": 40,
    "大理石": 41,
    "徐记小吃素粉": 42,
    "贵州东方驾校科目二训练场": 43,
    "金竹派出所贵州省农科院附中执勤点": 44,
    "贵州省农业科学院": 45,
    "贵阳市林城苗苗小学": 46,
    "133县道": 47,
    "贵阳阿哈湖国家湿地公园-廊桥烟溪": 48,
    "梯田湿地": 49,
    "龙云雕刻石材有限公司贵州办事处": 50,
    "应腾达科目二考场": 51,
    "土黄牛肉馆(2店)": 52,
    "贵阳市南明区苗苗实验学校": 53,
    "秘招专治颈椎": 54,
    "后坝派出所": 55,
    "飞来山": 56,
    "新建汽制厂幼儿园": 57,
    "金关社区贵轮居委会": 58,
    "百花大道地铁站D口": 59,
    "北京西路": 60
  }
}