{
  "百马大道": 723,
  "逍遥山庄": 1819,
  "逸坤·尚品": 818,
  "聚能汽车服务中心": 532,
  "广汽广瑞通清镇店": 584,
  "清镇市建材水泥制品厂": 496,
  "茶语饭叙": 516,
  "聚源家私": 2755,
  "贵州彬源管业有限公司": 648,
  "精校传动轴": 584,
  "林东中学": 456,
  "建安三幼": 460,
  "贵黄高速": 554,
  "蒿芝小学": 512,
  "邓坡路": 1199,
  "观清路辅路": 769,
  "金清立交": 691,
  "客乐居商务酒店(金阳客车站店)": 472,
  "贵阳幸福商务宾馆": 492,
  "柏曼酒店贵阳西南商贸城金阳客车站店大堂": 549,
  "杨春会活油土烙锅(碧桂园·观山府店)": 499,
  "豆腐皮火锅": 472,
  "宾阳街道社区卫生服务中心": 533,
  "金源社区小箐村微型消防站": 873,
  "胖子烤肉(中铁逸都店)": 1060,
  "彝寨杀猪粉": 644,
  "中国邮政储蓄银行(世纪城营业所)": 454,
  "煌上煌酱鸭(观山湖福州街店)": 803,
  "珍珠泉街": 472,
  "石龙路": 458,
  "运荣荷城羊肉粉馆": 647,
  "贵阳世纪城龙耀苑": 502
}