{
  "up": {
    "1": "云岩区荷塘社区第二卫生服务站",
    "2": "五极家居(金龙国际中心店)",
    "3": "水电九局居委会",
    "4": "俞记安顺老面破酥包",
    "5": "遵义虾子羊肉粉(松岭路店)",
    "6": "纸上烤肉",
    "7": "贵阳市公安局观山湖分局金岭责任区刑警队",
    "8": "铜锣坊(麒龙商务港店)",
    "9": "小两口饭店",
    "10": "珍宝酒楼(金阳店)",
    "11": "贵阳和成快捷酒店",
    "12": "麒麟安心班",
    "13": "厨非",
    "14": "贵阳景天酒店(金融城店)",
    "15": "酸菜腊肉豆米火锅(知秋轩店)",
    "16": "粑粑坳街",
    "17": "艳山红村",
    "18": "茅公馆",
    "19": "尖坡小学乡村学校少年宫",
    "20": "121县道",
    "21": "贵阳国际陆港",
    "22": "都拉村",
    "23": "奔土村",
    "24": "第十一幼儿园",
    "25": "盐沙大道",
    "26": "中共都拉民族卫生院支部委员会",
    "27": "都溪垂柳公园",
    "28": "蓬莱仙界牌坊",
    "29": "中共上水村支部委员会",
    "30": "146县道",
    "31": "555村道",
    "32": "马寨湾"
  },
  "down": {
    "33": "马寨湾",
    "34": "555村道",
    "35": "146县道",
    "36": "中共上水村支部委员会",
    "37": "蓬莱仙界牌坊",
    "38": "都溪垂柳公园",
    "39": "中共都拉民族卫生院支部委员会",
    "40": "盐沙大道",
    "41": "第十一幼儿园",
    "42": "奔土村",
    "43": "都拉村",
    "44": "贵阳国际陆港",
    "45": "121县道",
    "46": "尖坡小学乡村学校少年宫",
    "47": "茅公馆",
    "48": "艳山红村",
    "49": "粑粑坳街",
    "50": "酸菜腊肉豆米火锅(知秋轩店)",
    "51": "贵阳景天酒店(金融城店)",
    "52": "厨非",
    "53": "麒麟安心班",
    "54": "贵阳和成快捷酒店",
    "55": "珍宝酒楼(金阳店)",
    "56": "小两口饭店",
    "57": "铜锣坊(麒龙商务港店)",
    "58": "贵阳市公安局观山湖分局金岭责任区刑警队",
    "59": "纸上烤肉",
    "60": "遵义虾子羊肉粉(松岭路店)",
    "61": "俞记安顺老面破酥包",
    "62": "水电九局居委会",
    "63": "五极家居(金龙国际中心店)",
    "64": "云岩区荷塘社区第二卫生服务站"
  }
}