{
  "up": {
    "白云大道": 1,
    "贵阳家园宾馆": 2,
    "贵州佳宇华昌货架厂": 3,
    "太阳能路灯": 4,
    "寅桐文化艺术学校": 5,
    "三桥社区卫生服务中心新冠疫苗接种点": 6,
    "正宗水城羊肉粉(贵龙园店)": 7,
    "转湾塘隧道": 8,
    "粮机厂宿舍": 9,
    "吉庆巷": 10,
    "海底捞火锅(汇金星力城店)": 11,
    "静元舞蹈星乐城总校": 12,
    "贵阳银行(瑞南支行)": 13,
    "中共滨河社区委员会": 14,
    "经协大厦(箭道街)": 15,
    "LOOP搬山吞海店": 16,
    "药王光达堂健康管理中心南明区旗舰店": 17,
    "花冠路辅路": 18,
    "成都铁路局贵阳车辆段后巢检修所": 19,
    "贵阳宏发汽车修理厂": 20,
    "贵阳市森林公园": 21,
    "龙洞堡大道": 22,
    "贵阳新月出租汽车有限公司": 23,
    "龙里国丰村镇银行新城支行": 24,
    "贵阳银鑫商务酒店": 25,
    "龙洞堡大道辅路": 26,
    "贵阳金黔商务酒店": 27,
    "沙地坡服务区": 28,
    "中国石油沙地坡服务区加油站": 29,
    "沙地坡服务区修理厂": 30,
    "秦祺收费站(G76厦蓉高速入口东南向)": 31
  },
  "down": {
    "秦祺收费站(G76厦蓉高速入口东南向)": 32,
    "沙地坡服务区修理厂": 33,
    "中国石油沙地坡服务区加油站": 34,
    "沙地坡服务区": 35,
    "贵阳金黔商务酒店": 36,
    "龙洞堡大道辅路": 37,
    "贵阳银鑫商务酒店": 38,
    "龙里国丰村镇银行新城支行": 39,
    "贵阳新月出租汽车有限公司": 40,
    "龙洞堡大道": 41,
    "贵阳市森林公园": 42,
    "贵阳宏发汽车修理厂": 43,
    "成都铁路局贵阳车辆段后巢检修所": 44,
    "花冠路辅路": 45,
    "药王光达堂健康管理中心南明区旗舰店": 46,
    "LOOP搬山吞海店": 47,
    "经协大厦(箭道街)": 48,
    "中共滨河社区委员会": 49,
    "贵阳银行(瑞南支行)": 50,
    "静元舞蹈星乐城总校": 51,
    "海底捞火锅(汇金星力城店)": 52,
    "吉庆巷": 53,
    "粮机厂宿舍": 54,
    "转湾塘隧道": 55,
    "正宗水城羊肉粉(贵龙园店)": 56,
    "三桥社区卫生服务中心新冠疫苗接种点": 57,
    "寅桐文化艺术学校": 58,
    "太阳能路灯": 59,
    "贵州佳宇华昌货架厂": 60,
    "贵阳家园宾馆": 61,
    "白云大道": 62
  }
}