{
  "观山隧道": 1081,
  "G6002贵阳绕城高速入口(瓮安方向)": 1197,
  "小堰": 534,
  "G6002贵阳绕城高速": 632,
  "文恋烟酒店": 580,
  "大沟坎": 2115,
  "开心农场": 1134,
  "贵阳乌当佳信塑胶厂": 504,
  "贵阳市乌当区东风镇新村村退役军人服务站": 784,
  "洛湾胖哥小豆腐烧烤店": 2079,
  "贵州奇花艺草兰花培育有限公司": 598,
  "乌当区教育科研与教师培训中心": 1101,
  "幸福里3期": 507,
  "绝味鸭脖(龙广路店)": 487,
  "江之味片片鱼(幸福里东部新城1期店)": 836,
  "贵阳经纬印刷厂": 654,
  "静红家常菜(悦景新城店)": 762,
  "新天派出所北衙村警务室": 512,
  "堡来乐(松溪园店)": 755,
  "当代贵州期刊传媒集团": 616,
  "宾隆超市(城市魔方店)": 450,
  "德克士(云岩万达广场店)": 640,
  "沙龙拌饭(中天花园叠翠谷店)": 543,
  "六龙豆干火锅(中天花园叠翠谷店)": 761,
  "德尔客(黄山冲路店)": 895,
  "黄南武阳朗辣子鸡(形象店)": 639,
  "盐务街道": 512,
  "贵州医科大学临床技能实验中心3-4教室": 583,
  "中华北路": 450
}