{
  "up": {
    "1": "贵州铁路技师学院-和尚坡铁路学校",
    "2": "贵和食府(三桥店)",
    "3": "三桥社区卫生服务",
    "4": "乔氏台球俱乐部",
    "5": "圣泉",
    "6": "头桥街道退役军人服务站",
    "7": "黔灵山公园-曲尺亭",
    "8": "贵阳市林业绿化局(北新区路)",
    "9": "天天房开枫园小区",
    "10": "麻辣馄饨店(安云路店)",
    "11": "贵阳市城市综合执法支队云岩大队驻省政府大院执法中队",
    "12": "蜜雪冰城(兴贵路店)",
    "13": "益天颐添",
    "14": "中国银行(大营坡支行)",
    "15": "贵阳亨驿鸿客栈",
    "16": "知行路",
    "17": "田田教育(中天校区)",
    "18": "城市魔方",
    "19": "贵州省妇幼保健院总院",
    "20": "潜江小龙虾(恒大雅苑2栋店)",
    "21": "贵阳市乌当区民族宗教事务局",
    "22": "燕子冲",
    "23": "罗记肠旺面湖南面(悦景新城店)",
    "24": "公馆路",
    "25": "饭粉面(幸福里东部新城1期店)",
    "26": "贵阳市乌当区消防救援大队",
    "27": "7天连锁酒店(贵阳新添美食街店)",
    "28": "高新北路",
    "29": "国家税务总局贵阳市乌当区税务局第一税务分局",
    "30": "爱康牙科"
  },
  "down": {
    "31": "爱康牙科",
    "32": "国家税务总局贵阳市乌当区税务局第一税务分局",
    "33": "高新北路",
    "34": "7天连锁酒店(贵阳新添美食街店)",
    "35": "贵阳市乌当区消防救援大队",
    "36": "饭粉面(幸福里东部新城1期店)",
    "37": "公馆路",
    "38": "罗记肠旺面湖南面(悦景新城店)",
    "39": "燕子冲",
    "40": "贵阳市乌当区民族宗教事务局",
    "41": "潜江小龙虾(恒大雅苑2栋店)",
    "42": "贵州省妇幼保健院总院",
    "43": "城市魔方",
    "44": "田田教育(中天校区)",
    "45": "知行路",
    "46": "贵阳亨驿鸿客栈",
    "47": "中国银行(大营坡支行)",
    "48": "益天颐添",
    "49": "蜜雪冰城(兴贵路店)",
    "50": "贵阳市城市综合执法支队云岩大队驻省政府大院执法中队",
    "51": "麻辣馄饨店(安云路店)",
    "52": "天天房开枫园小区",
    "53": "贵阳市林业绿化局(北新区路)",
    "54": "黔灵山公园-曲尺亭",
    "55": "头桥街道退役军人服务站",
    "56": "圣泉",
    "57": "乔氏台球俱乐部",
    "58": "三桥社区卫生服务",
    "59": "贵和食府(三桥店)",
    "60": "贵州铁路技师学院-和尚坡铁路学校"
  }
}