{
  "up": {
    "金关社区贵轮居委会": 1,
    "星羽网咖(数博万达店)": 2,
    "贵阳市观山湖区第六中学": 3,
    "贵州工业职业技术学院生活区": 4,
    "思妮尔视力养护中心": 5,
    "齐记小笼包(恒大滨河左岸店)": 6,
    "北京市体检中心合作中心": 7,
    "小冬哥羊肉粉馆(金谷苑店)": 8,
    "豆豆甜品店(碧海花园店)": 9,
    "藏灸养生馆": 10,
    "彩虹屋私房菜(碧海花园丽阳天下店)": 11,
    "德克士(元盛店)": 12,
    "桃林路": 13,
    "重庆舒炳记老火锅(绿地联盛店)": 14,
    "富力中心": 15,
    "贵阳市观山湖区消防救援大队": 16,
    "千里明视力康复保健中心": 17,
    "西普陀寺-鼓楼": 18,
    "夜朗水八碗(夜朗古城)": 19,
    "天林花园2期": 20,
    "王先森活仙人麻辣香锅(朝晖花园留云庭B区店)": 21,
    "龙腾香辣粉面馆": 22,
    "G6002贵阳绕城高速": 23,
    "新世界家具批发城": 24,
    "蓝天白云幼儿园": 25,
    "农家腊肉豆米火锅店": 26,
    "贵阳享逸宾馆": 27,
    "贵阳家庭商务宾馆": 28,
    "螃蟹田": 29,
    "螃蟹田垂钓乐园": 30
  },
  "down": {
    "螃蟹田垂钓乐园": 31,
    "螃蟹田": 32,
    "贵阳家庭商务宾馆": 33,
    "贵阳享逸宾馆": 34,
    "农家腊肉豆米火锅店": 35,
    "蓝天白云幼儿园": 36,
    "新世界家具批发城": 37,
    "G6002贵阳绕城高速": 38,
    "龙腾香辣粉面馆": 39,
    "王先森活仙人麻辣香锅(朝晖花园留云庭B区店)": 40,
    "天林花园2期": 41,
    "夜朗水八碗(夜朗古城)": 42,
    "西普陀寺-鼓楼": 43,
    "千里明视力康复保健中心": 44,
    "贵阳市观山湖区消防救援大队": 45,
    "富力中心": 46,
    "重庆舒炳记老火锅(绿地联盛店)": 47,
    "桃林路": 48,
    "德克士(元盛店)": 49,
    "彩虹屋私房菜(碧海花园丽阳天下店)": 50,
    "藏灸养生馆": 51,
    "豆豆甜品店(碧海花园店)": 52,
    "小冬哥羊肉粉馆(金谷苑店)": 53,
    "北京市体检中心合作中心": 54,
    "齐记小笼包(恒大滨河左岸店)": 55,
    "思妮尔视力养护中心": 56,
    "贵州工业职业技术学院生活区": 57,
    "贵阳市观山湖区第六中学": 58,
    "星羽网咖(数博万达店)": 59,
    "金关社区贵轮居委会": 60
  }
}