{
  "马老武麻辣牛肉火锅(福建路店)": 570,
  "湘雅蒸菜(世纪城店)": 497,
  "安顺破酥包子店": 534,
  "贵州省环境科学研究设计院": 580,
  "雅士居": 433,
  "远大·生态风景": 1271,
  "鼎釜羹海鲜粤菜熟食店": 635,
  "煮意皇牛鲜牛肉火锅(会展城店)": 419,
  "味长沙湘掌勺餐饮(美的·林城时代南区店)": 444,
  "中裕舞蹈": 457,
  "贵阳市公安交通管理局白云区分局": 551,
  "泉上发现(金融店)": 841,
  "荷放艺术工作室(装修中)": 490,
  "杉坡": 1163,
  "金仕奎便利店": 968,
  "贵阳北公安交警执法站": 2340,
  "尖坡互通": 624,
  "七笼饺": 802,
  "贵遵高速": 987,
  "冷水村村委会": 656,
  "都拉益智树幼儿园": 844,
  "保税区出口(G6002贵阳绕城高速东向)": 639,
  "伴山别院餐厅": 640,
  "G6002贵阳绕城高速": 575,
  "王幺娘老字号洋芋粑": 698,
  "白云区都新社区居民议事会": 420,
  "贵阳乾元冷链物流有限公司": 676,
  "G6002贵阳绕城高速入口(凯里方向)": 579,
  "滥坝": 2044,
  "北京东路": 1147,
  "云开二级公路": 1386,
  "小张牛肉粉面馆": 1062
}