{
  "高星汇·乐湾国际训练中心": 505,
  "筑箐苑2号山庄": 1464,
  "贵阳汇砼建材有限公司": 1458,
  "大岔": 1038,
  "情人谷路口(公交站)": 543,
  "曜阳路": 536,
  "阿栗杨梅园山庄地面停车场(出入口)": 517,
  "大转弯安置小区": 651,
  "高枧1号大桥": 665,
  "夜猫子竹签烤肉(中天甜蜜小镇2组团店)": 706,
  "中天pluss": 1621,
  "馋猫小黄鱼": 773,
  "贵阳和谐阳光酒店": 552,
  "有故事烤鸡(未来方舟F10组团店)": 581,
  "刘丽特色豆干火锅(二分店)": 511,
  "金狮小区顺海苑足球场": 1499,
  "莱贝湾艺术智能幼儿园": 545,
  "学孚教育": 1043,
  "黔北特色灌汤小肠火锅(兴贵路店)": 637,
  "市北路38号院": 542,
  "牧以众康": 591,
  "李记卤烫": 541,
  "生态环保纪念碑": 599,
  "贵州省肿瘤医院综合楼": 712,
  "贵州医科大学附属肿瘤医院放疗楼": 903,
  "贵阳印象小区": 692,
  "西二环": 493,
  "贵州众源星宝汽车服务有限公司": 845,
  "九宫格重庆老火锅": 534,
  "避风塘茶饮(白云大道店)": 677
}