{
  "up": {
    "贵州产业技术发展研究院": 1,
    "桔子水晶贵阳会展中心酒店": 2,
    "盘州吴记铜锅牛肉天一国际店": 3,
    "贵阳悦程医院": 4,
    "黔之牧牛馆": 5,
    "思响堆潮流街舞": 6,
    "万达影城(数博万达广场店)": 7,
    "掏耳朵": 8,
    "圣泉社区分院": 9,
    "深沥摩托车维修部": 10,
    "下五里女子职业学校": 11,
    "弘福寺-五观堂": 12,
    "七冲路": 13,
    "王大娘牛羊肉粉馆": 14,
    "苏记羊杂牛肉粉(金色家园店)": 15,
    "向日葵二幼": 16,
    "花果园2期": 17,
    "贵州省建筑医院": 18,
    "国家税务总局贵阳市南明区税务局政务中心办税服务厅": 19,
    "工贸小区": 20,
    "金海岸": 21,
    "中共南明区委党校远程教育B级站": 22,
    "南明天官口腔": 23,
    "朝阳村委会(沙南巷)": 24,
    "贵阳药用资源博物馆": 25,
    "阿幼朵文化艺术中心": 26,
    "王哥豆花饭豆花面": 27,
    "古益通筋骨养生馆(小河二店)": 28,
    "小河邮政商住楼": 29,
    "优莱客汉堡奶茶(小河店)": 30,
    "新口味北方馒头王(明河路店)": 31,
    "印象实验幼儿园": 32,
    "贵阳市花溪区第十小学乡村少年宫": 33
  },
  "down": {
    "贵阳市花溪区第十小学乡村少年宫": 34,
    "印象实验幼儿园": 35,
    "新口味北方馒头王(明河路店)": 36,
    "优莱客汉堡奶茶(小河店)": 37,
    "小河邮政商住楼": 38,
    "古益通筋骨养生馆(小河二店)": 39,
    "王哥豆花饭豆花面": 40,
    "阿幼朵文化艺术中心": 41,
    "贵阳药用资源博物馆": 42,
    "朝阳村委会(沙南巷)": 43,
    "南明天官口腔": 44,
    "中共南明区委党校远程教育B级站": 45,
    "金海岸": 46,
    "工贸小区": 47,
    "国家税务总局贵阳市南明区税务局政务中心办税服务厅": 48,
    "贵州省建筑医院": 49,
    "花果园2期": 50,
    "向日葵二幼": 51,
    "苏记羊杂牛肉粉(金色家园店)": 52,
    "王大娘牛羊肉粉馆": 53,
    "七冲路": 54,
    "弘福寺-五观堂": 55,
    "下五里女子职业学校": 56,
    "深沥摩托车维修部": 57,
    "圣泉社区分院": 58,
    "掏耳朵": 59,
    "万达影城(数博万达广场店)": 60,
    "思响堆潮流街舞": 61,
    "黔之牧牛馆": 62,
    "贵阳悦程医院": 63,
    "盘州吴记铜锅牛肉天一国际店": 64,
    "桔子水晶贵阳会展中心酒店": 65,
    "贵州产业技术发展研究院": 66
  }
}