{
  "九画艺术培训": 664,
  "贵黄高速入口(西南向)": 716,
  "贵州桥梁建设集团有限责任公司公路交通工程分公司": 628,
  "茶语饭叙": 648,
  "清镇市第三实验小学": 2887,
  "贵黄高速": 780,
  "贵州常青环保有限公司": 716,
  "贵州新格标识工程有限公司": 588,
  "建安三幼": 592,
  "广大城": 686,
  "观清路": 644,
  "上枧村(公交站)": 1331,
  "贵阳鑫恒晶木业": 901,
  "辉蝶水暖洁具批发": 823,
  "摆岗坡隧道": 604,
  "金阳客车站": 624,
  "柏曼酒店贵阳西南商贸城金阳客车站店大堂": 681,
  "豪杰宾馆": 631,
  "观山湖区外国语实验中学·南校区": 604,
  "艾了教育": 665,
  "贵阳高仕通商务酒店": 1005,
  "云潭南路(南)(快速公交站)": 1192,
  "福艳口腔门诊": 776,
  "贵阳流星公寓": 586,
  "贵州乌当农商银行(世纪城支行)": 935,
  "珍珠泉街": 604,
  "领动机器人(贵阳校区)": 590,
  "运荣荷城羊肉粉馆": 1000,
  "贵阳银行(观山湖支行)": 665
}