{
  "up": {
    "1": "贵阳北站出口(中环路北段西南向)",
    "2": "立央水城羊肉粉(保利云山店)",
    "3": "贵阳实验小学云山分校",
    "4": "跳皮小豆腐坨坨肉(天誉城店)",
    "5": "地母洞",
    "6": "鹿冲关站(快速公交站)",
    "7": "青年舍",
    "8": "贵州省植物园",
    "9": "披萨物语",
    "10": "御景湾",
    "11": "冒沙井路",
    "12": "吉布鲁牛排海鲜自助(云岩万达广场店)",
    "13": "张晓洁缸缸麻辣烫(恒大雅苑店)",
    "14": "天意私厨(恒大雅苑店)",
    "15": "卢记杭州小笼包(松溪园店)",
    "16": "水锦花都",
    "17": "胖姐小豆腐(新添寨北衙路店)",
    "18": "泉天下·国际公馆-四湖区",
    "19": "贵阳市乌当区红星家长学校",
    "20": "贵阳市乌当区红星小学",
    "21": "贵阳市乌当区水东实验学校",
    "22": "光明画室",
    "23": "光明路",
    "24": "中国邮政储蓄银行(东风支行)",
    "25": "堡子路",
    "26": "乌当卫生院",
    "27": "贵州妇女儿童国际医院(建设中)",
    "28": "贵阳乐湾温泉酒店",
    "29": "新河大桥",
    "30": "贵黔国际总医院新冠疫苗接种点",
    "31": "贵州龙行畅游旅游客运有限公司",
    "32": "洛湾(地铁站)",
    "33": "老兵土碗菜"
  },
  "down": {
    "34": "老兵土碗菜",
    "35": "洛湾(地铁站)",
    "36": "贵州龙行畅游旅游客运有限公司",
    "37": "贵黔国际总医院新冠疫苗接种点",
    "38": "新河大桥",
    "39": "贵阳乐湾温泉酒店",
    "40": "贵州妇女儿童国际医院(建设中)",
    "41": "乌当卫生院",
    "42": "堡子路",
    "43": "中国邮政储蓄银行(东风支行)",
    "44": "光明路",
    "45": "光明画室",
    "46": "贵阳市乌当区水东实验学校",
    "47": "贵阳市乌当区红星小学",
    "48": "贵阳市乌当区红星家长学校",
    "49": "泉天下·国际公馆-四湖区",
    "50": "胖姐小豆腐(新添寨北衙路店)",
    "51": "水锦花都",
    "52": "卢记杭州小笼包(松溪园店)",
    "53": "天意私厨(恒大雅苑店)",
    "54": "张晓洁缸缸麻辣烫(恒大雅苑店)",
    "55": "吉布鲁牛排海鲜自助(云岩万达广场店)",
    "56": "冒沙井路",
    "57": "御景湾",
    "58": "披萨物语",
    "59": "贵州省植物园",
    "60": "青年舍",
    "61": "鹿冲关站(快速公交站)",
    "62": "地母洞",
    "63": "跳皮小豆腐坨坨肉(天誉城店)",
    "64": "贵阳实验小学云山分校",
    "65": "立央水城羊肉粉(保利云山店)",
    "66": "贵阳北站出口(中环路北段西南向)"
  }
}