{
  "北京仙富癫痫病医学研究院清镇市分院": 412,
  "六盘水老牌牛羊肉粉": 432,
  "清镇市第三实验小学": 2671,
  "新隆砖厂": 564,
  "320国道": 500,
  "贵黄高速": 372,
  "云峰寺": 376,
  "广大城": 470,
  "G60沪昆高速": 428,
  "贵阳朗升汽车服务有限公司": 1115,
  "麦格纳座椅(贵阳)有限公司": 685,
  "贵阳消防应急救援综合训练基地": 607,
  "贵安驾校(金华分校)": 388,
  "金华派出所干井村委会警务助理工作站": 408,
  "干井大桥": 465,
  "常寿堂": 415,
  "观山湖区外国语实验中学·南校区": 388,
  "宾阳街道社区卫生服务中心": 449,
  "仙客来食坊": 789,
  "中共贵州广播电视大学委员会(云潭南路)": 1013,
  "小食代·土黄牛肉粉": 492,
  "T加齿科": 750,
  "亚丹定制家居(世纪金源购物中心店)": 362,
  "来一缸羊肉粉(龙泉店)": 419,
  "禾呈记豆花面馆": 441,
  "格林宴会中心": 962,
  "惠诚滋知(轮胎厂店)": 460,
  "贵阳平顺宾馆": 432,
  "贵阳市云岩区艾贝幼儿园": 503,
  "未来之星幼儿园(飞来巷)": 943
}