{
  "up": {
    "贵州正祥法医物证司法鉴定所": 1,
    "燕子烧烤(阳关小区店)": 2,
    "融创数据小镇": 3,
    "黔味食筑·盘州牛肉(麒龙商务港A座店)": 4,
    "通号·云璟台": 5,
    "贵阳毛十八交通工程有限公司": 6,
    "黔航小区": 7,
    "松岭路": 8,
    "诚意养生服务馆": 9,
    "北京西路": 10,
    "黔城美景": 11,
    "龙福花园": 12,
    "萌之蓝幼儿园": 13,
    "花果园U区南区": 14,
    "蔡关路": 15,
    "豆豆实验室": 16,
    "凯诚驾校(南明店)": 17,
    "云上小座 (屋顶花园烧烤)": 18,
    "贵阳阿哈湖国家湿地公园-花谷": 19,
    "竹林村农家书屋": 20,
    "上坝": 21,
    "勤奋学校": 22,
    "贵阳银行(中曹支行)": 23,
    "川味食族家常菜馆(花溪大道店)": 24,
    "贵阳西站": 25,
    "贵州多元素文化传媒有限公司": 26,
    "董家堰居委会(花溪大道南段)": 27,
    "贵州民族大学音乐舞蹈学院": 28,
    "贵阳宏翼宾馆": 29,
    "中共贵州民族大学委员会党校预科教育学院分校": 30,
    "纯野菜砂锅酸辣汤": 31,
    "竹林转运站": 32
  },
  "down": {
    "竹林转运站": 33,
    "纯野菜砂锅酸辣汤": 34,
    "中共贵州民族大学委员会党校预科教育学院分校": 35,
    "贵阳宏翼宾馆": 36,
    "贵州民族大学音乐舞蹈学院": 37,
    "董家堰居委会(花溪大道南段)": 38,
    "贵州多元素文化传媒有限公司": 39,
    "贵阳西站": 40,
    "川味食族家常菜馆(花溪大道店)": 41,
    "贵阳银行(中曹支行)": 42,
    "勤奋学校": 43,
    "上坝": 44,
    "竹林村农家书屋": 45,
    "贵阳阿哈湖国家湿地公园-花谷": 46,
    "云上小座 (屋顶花园烧烤)": 47,
    "凯诚驾校(南明店)": 48,
    "豆豆实验室": 49,
    "蔡关路": 50,
    "花果园U区南区": 51,
    "萌之蓝幼儿园": 52,
    "龙福花园": 53,
    "黔城美景": 54,
    "北京西路": 55,
    "诚意养生服务馆": 56,
    "松岭路": 57,
    "黔航小区": 58,
    "贵阳毛十八交通工程有限公司": 59,
    "通号·云璟台": 60,
    "黔味食筑·盘州牛肉(麒龙商务港A座店)": 61,
    "融创数据小镇": 62,
    "燕子烧烤(阳关小区店)": 63,
    "贵州正祥法医物证司法鉴定所": 64
  }
}