{
  "up": {
    "1": "柴老弟素粉馆(世纪城金源街店)",
    "2": "圣马钛诺一艺术成长中心",
    "3": "凯瑞琴行",
    "4": "楼脚酸汤牛肉(恒大中央广场店)",
    "5": "贵阳寻息阁酒店(贵阳北京西路世纪城店)",
    "6": "谢云贵清香水煮鸡数博万达店",
    "7": "乔老爷私房菜(白云大道店)",
    "8": "流云食府(圣泉流云花园店)",
    "9": "云岩富民村镇银行三桥支行",
    "10": "贵州贵龙驾校",
    "11": "黔春路站(快速公交站)",
    "12": "三岭湾",
    "13": "白象泉",
    "14": "云岩吾悦广场(建设中)",
    "15": "贵阳肠旺面鸭块粉面(总店)",
    "16": "成博高中生午托园",
    "17": "贵州医科大学-临床前药物研究所",
    "18": "天津灌汤小笼包(百花山店)",
    "19": "银发小菜馆",
    "20": "童康乐语",
    "21": "渔安立交",
    "22": "贵阳老素粉(中环路东段店)",
    "23": "云岩区政务大厅办税服务窗口",
    "24": "滋味厨房",
    "25": "中天甜蜜小镇",
    "26": "中天甜蜜小镇3组团",
    "27": "北龙立交",
    "28": "情人谷路",
    "29": "高枧1号大桥",
    "30": "福祥宴柴火鸡",
    "31": "情人谷"
  },
  "down": {
    "32": "情人谷",
    "33": "福祥宴柴火鸡",
    "34": "高枧1号大桥",
    "35": "情人谷路",
    "36": "北龙立交",
    "37": "中天甜蜜小镇3组团",
    "38": "中天甜蜜小镇",
    "39": "滋味厨房",
    "40": "云岩区政务大厅办税服务窗口",
    "41": "贵阳老素粉(中环路东段店)",
    "42": "渔安立交",
    "43": "童康乐语",
    "44": "银发小菜馆",
    "45": "天津灌汤小笼包(百花山店)",
    "46": "贵州医科大学-临床前药物研究所",
    "47": "成博高中生午托园",
    "48": "贵阳肠旺面鸭块粉面(总店)",
    "49": "云岩吾悦广场(建设中)",
    "50": "白象泉",
    "51": "三岭湾",
    "52": "黔春路站(快速公交站)",
    "53": "贵州贵龙驾校",
    "54": "云岩富民村镇银行三桥支行",
    "55": "流云食府(圣泉流云花园店)",
    "56": "乔老爷私房菜(白云大道店)",
    "57": "谢云贵清香水煮鸡数博万达店",
    "58": "贵阳寻息阁酒店(贵阳北京西路世纪城店)",
    "59": "楼脚酸汤牛肉(恒大中央广场店)",
    "60": "凯瑞琴行",
    "61": "圣马钛诺一艺术成长中心",
    "62": "柴老弟素粉馆(世纪城金源街店)"
  }
}