{
  "贵安草莓园": 3279,
  "普洛斯贵阳铁路港物流园": 990,
  "贵州省体育局清镇训练基地(西北门)": 768,
  "雪芳化验室收样处": 1864,
  "北京现代(贵州京典店)": 863,
  "济辉汽车城": 577,
  "美亚歌KTV": 629,
  "清远机动车检测": 541,
  "清镇市巢凤大道碧桂园茶马古镇凤鸣苑": 561,
  "清镇市龙滩幼儿园家长学校": 2800,
  "清镇市政务中心交通警察大队车管所审验教育学习室": 693,
  "精校传动轴": 629,
  "超诚工业园": 501,
  "云峰寺": 505,
  "蒿芝居委会": 599,
  "华联万家购物(林东店)": 557,
  "观清路": 1244,
  "邓坡": 814,
  "小茶山": 736,
  "观山湖区摩托车考试中心黔湖摩托车考场": 517,
  "北京西路": 537,
  "车辆管理所贵阳西南国际商贸城业务大厅": 594,
  "原汤羊肉粉": 544,
  "常寿堂": 517,
  "观山湖区外国语实验中学·南校区": 578,
  "贵州职业技术学院": 918,
  "广州路": 1105,
  "卓雅舞蹈": 689,
  "中国民生银行(贵阳金阳南路支行)": 499,
  "世纪花甲": 836,
  "但家香酥鸭(金阳福州街店)": 508,
  "目视明视力训练服务中心(世纪城店)": 742,
  "贵州银行(世纪城兴福路支行)": 695
}