{
  "特百惠(北京华联二桥专卖店)": 421,
  "贵龙园": 503,
  "黔灵山国际社区": 917,
  "CC英语(三桥北路店)": 689,
  "天合水暖卫浴批发部": 412,
  "贵阳农商银行(改茶支行)": 754,
  "俞记安顺老面破酥包": 458,
  "粼圆梦家学教育": 657,
  "林城口腔": 429,
  "诚忠堂": 590,
  "都匀路": 849,
  "四川球溪鲶鱼": 462,
  "振华宇光": 1052,
  "塞纳左岸咖啡音乐主题西餐厅(会展城旗舰店)": 406,
  "中国农业银行(贵州名仕分理处)": 886,
  "恺跃酒店(会展店)": 631,
  "中天润玺": 419,
  "炳旭天津灌汤小笼包(长岭阳光店)": 415,
  "均运检测站": 431,
  "白云区气象局": 967,
  "森林狼炭火烤羊腿(贵阳总店)": 1131,
  "田田教育(白云缤纷校区)": 411,
  "正新鸡排(奥马店)": 930,
  "贵阳市白云区第一小学": 529,
  "乡村辣子鸡": 1050,
  "曹关湿地公园": 468,
  "袁老四重庆火锅(贵阳北尚华城店)": 840,
  "小兵烧烤韩记小豆腐(马掌坡路店)": 599,
  "源森木格全屋定制": 612,
  "杰优水果店": 1717
}