{
  "蓝馨幼儿园": 651,
  "王武南巷": 1175,
  "华瑞学校": 1157,
  "小珠显": 525,
  "大兴星城金佰利": 669,
  "杰汇华府双语": 556,
  "初芯音乐教育": 612,
  "中共贵阳市交通技工学校总支委员会": 529,
  "贵州巧媳妇食品有限公司": 673,
  "晓桂汽修": 1251,
  "宏远汽车汽修养护中心": 661,
  "甲秀翠微小学": 1463,
  "贡茶(大剧院店)": 621,
  "中国建设银行(贵阳新华支行)": 560,
  "小亮粉面店": 550,
  "文化路78号院落": 543,
  "贵阳市总工会信访接待室": 821,
  "贵阳脉通血管医院发热门诊": 564,
  "惠诚滋知(汇金星力城店)": 542,
  "北京刷羊肉火锅": 566,
  "中信银行(贵阳黔灵支行)": 708,
  "铁路小区": 529,
  "古逸堂书法工作室": 740,
  "中寨": 931,
  "熊二烧烤(圣泉路店)": 846,
  "圣泉社区卫生服务站": 575,
  "圣宠宠物(云岩区店)": 1006,
  "屈福记金沙牛羊肉粉面馆": 577,
  "贵州交通职业技术学院北院建筑工程系": 1157,
  "刘大哥辣子鸡": 604
}