{
  "up": {
    "1": "怪兽充电(黔灵湖山庄)",
    "2": "中环路西段入口(北向)",
    "3": "富力华庭",
    "4": "北京华联超市(二桥黔春路店)",
    "5": "贵阳珺怡大酒店",
    "6": "滋味园食府(碧玉园店)",
    "7": "福建千里香馄饨(三桥南路店)",
    "8": "云岩区头桥社区居民议事委员会",
    "9": "CITY PARK 西派国樾",
    "10": "贵州龙(威清店)",
    "11": "徐鼎聚北京烤鸭",
    "12": "陕西路127号院",
    "13": "贵州医科大学-花溪校区管委会",
    "14": "大自然棕床垫(贵开路店)",
    "15": "医联体",
    "16": "金健康营养自助工程",
    "17": "真爱幼幼全日制早教云岩中心",
    "18": "村上一品精致日料(未来方舟店)",
    "19": "贵阳老素粉(中环路东段店)",
    "20": "云岩区人民政府政务服务大厅",
    "21": "贵美医学美容",
    "22": "中天甜蜜小镇",
    "23": "贵州华策若云文化传媒有限公司",
    "24": "128县道",
    "25": "北龙立交",
    "26": "高枧1号大桥",
    "27": "情人谷路",
    "28": "情人谷路口(公交站)",
    "29": "贵阳市曜阳养老服务中心",
    "30": "后所"
  },
  "down": {
    "31": "后所",
    "32": "贵阳市曜阳养老服务中心",
    "33": "情人谷路口(公交站)",
    "34": "情人谷路",
    "35": "高枧1号大桥",
    "36": "北龙立交",
    "37": "128县道",
    "38": "贵州华策若云文化传媒有限公司",
    "39": "中天甜蜜小镇",
    "40": "贵美医学美容",
    "41": "云岩区人民政府政务服务大厅",
    "42": "贵阳老素粉(中环路东段店)",
    "43": "村上一品精致日料(未来方舟店)",
    "44": "真爱幼幼全日制早教云岩中心",
    "45": "金健康营养自助工程",
    "46": "医联体",
    "47": "大自然棕床垫(贵开路店)",
    "48": "贵州医科大学-花溪校区管委会",
    "49": "陕西路127号院",
    "50": "徐鼎聚北京烤鸭",
    "51": "贵州龙(威清店)",
    "52": "CITY PARK 西派国樾",
    "53": "云岩区头桥社区居民议事委员会",
    "54": "福建千里香馄饨(三桥南路店)",
    "55": "滋味园食府(碧玉园店)",
    "56": "贵阳珺怡大酒店",
    "57": "北京华联超市(二桥黔春路店)",
    "58": "富力华庭",
    "59": "中环路西段入口(北向)",
    "60": "怪兽充电(黔灵湖山庄)"
  }
}