{
  "up": {
    "党建文化进百院啤酒厂宿舍": 1,
    "便宜货架": 2,
    "中医99养生馆": 3,
    "金鸭村": 4,
    "金关巷": 5,
    "贵阳市旅游学校": 6,
    "金城商务宾馆": 7,
    "贵阳世纪城购物中心智选假日酒店": 8,
    "楠火锅(观山湖店)": 9,
    "观山湖区第十幼儿园": 10,
    "龙吉路": 11,
    "CGV影城(印象城购物中心店)": 12,
    "逸峰": 13,
    "凯苗酸汤牛肉火锅(逸都店)": 14,
    "精品带皮牛肉粉(贵阳二铺总店)": 15,
    "金源社区小箐村微型消防站": 16,
    "余庆乡村剔骨鸭(商城东路店)": 17,
    "柏曼酒店贵阳西南商贸城金阳客车站店大堂": 18,
    "iu酒店(贵阳西南商贸城金阳客运站店)": 19,
    "休闲宾馆": 20,
    "摆岗坡隧道": 21,
    "贵州吉利汽车部件有限公司": 22,
    "心邻小屋-何官小学心理服务站": 23,
    "黔贵交通职业培训学校": 24,
    "蒿芝塘": 25,
    "金华派出所": 26,
    "320国道": 27,
    "超诚工业园": 28,
    "邢氏兄弟斗车加工厂": 29,
    "下甫二妹早餐店": 30,
    "清镇市龙滩幼儿园家长学校": 31,
    "龙滩": 32,
    "茶语饭叙": 33
  },
  "down": {
    "茶语饭叙": 34,
    "龙滩": 35,
    "清镇市龙滩幼儿园家长学校": 36,
    "下甫二妹早餐店": 37,
    "邢氏兄弟斗车加工厂": 38,
    "超诚工业园": 39,
    "320国道": 40,
    "金华派出所": 41,
    "蒿芝塘": 42,
    "黔贵交通职业培训学校": 43,
    "心邻小屋-何官小学心理服务站": 44,
    "贵州吉利汽车部件有限公司": 45,
    "摆岗坡隧道": 46,
    "休闲宾馆": 47,
    "iu酒店(贵阳西南商贸城金阳客运站店)": 48,
    "柏曼酒店贵阳西南商贸城金阳客车站店大堂": 49,
    "余庆乡村剔骨鸭(商城东路店)": 50,
    "金源社区小箐村微型消防站": 51,
    "精品带皮牛肉粉(贵阳二铺总店)": 52,
    "凯苗酸汤牛肉火锅(逸都店)": 53,
    "逸峰": 54,
    "CGV影城(印象城购物中心店)": 55,
    "龙吉路": 56,
    "观山湖区第十幼儿园": 57,
    "楠火锅(观山湖店)": 58,
    "贵阳世纪城购物中心智选假日酒店": 59,
    "金城商务宾馆": 60,
    "贵阳市旅游学校": 61,
    "金关巷": 62,
    "金鸭村": 63,
    "中医99养生馆": 64,
    "便宜货架": 65,
    "党建文化进百院啤酒厂宿舍": 66
  }
}