{
  "up": {
    "1": "织金土烙锅(金源街店)",
    "2": "贵阳星晨公寓",
    "3": "视野联行眼镜(世纪金源店)",
    "4": "中国邮政储蓄银行(世纪城营业所)",
    "5": "中天·帝景传说C区",
    "6": "观山湖区第二十五幼儿园",
    "7": "张炜狗肉羊肉火锅店",
    "8": "交通大数据研发中心",
    "9": "碧桂园·西南上城",
    "10": "豆腐皮火锅",
    "11": "商城西路",
    "12": "东旭宾馆(贵阳金阳新客车站店)",
    "13": "贵吉宾馆",
    "14": "摆岗坡隧道",
    "15": "黔湖驾校科三场地",
    "16": "金华镇汽车产业园社区卫生服务中心",
    "17": "金华派出所",
    "18": "贵阳市观山湖区远大小学集团校",
    "19": "广大城·耀晟一期",
    "20": "蒿芝居委会",
    "21": "G60沪昆高速",
    "22": "上铺村基层综合性文化服务中心",
    "23": "中共伟宏社区委员会",
    "24": "特色砂锅酸辣烫",
    "25": "华晨金杯(清镇店)",
    "26": "安稳汽修厂",
    "27": "德云堂理疗馆",
    "28": "农村金融服务站",
    "29": "草根绝味鸭脖(董家田公租房店)",
    "30": "郭记餐馆"
  },
  "down": {
    "31": "郭记餐馆",
    "32": "草根绝味鸭脖(董家田公租房店)",
    "33": "农村金融服务站",
    "34": "德云堂理疗馆",
    "35": "安稳汽修厂",
    "36": "华晨金杯(清镇店)",
    "37": "特色砂锅酸辣烫",
    "38": "中共伟宏社区委员会",
    "39": "上铺村基层综合性文化服务中心",
    "40": "G60沪昆高速",
    "41": "蒿芝居委会",
    "42": "广大城·耀晟一期",
    "43": "贵阳市观山湖区远大小学集团校",
    "44": "金华派出所",
    "45": "金华镇汽车产业园社区卫生服务中心",
    "46": "黔湖驾校科三场地",
    "47": "摆岗坡隧道",
    "48": "贵吉宾馆",
    "49": "东旭宾馆(贵阳金阳新客车站店)",
    "50": "商城西路",
    "51": "豆腐皮火锅",
    "52": "碧桂园·西南上城",
    "53": "交通大数据研发中心",
    "54": "张炜狗肉羊肉火锅店",
    "55": "观山湖区第二十五幼儿园",
    "56": "中天·帝景传说C区",
    "57": "中国邮政储蓄银行(世纪城营业所)",
    "58": "视野联行眼镜(世纪金源店)",
    "59": "贵阳星晨公寓",
    "60": "织金土烙锅(金源街店)"
  }
}