{
  "圣仕非舟幼儿园": 631,
  "贵遵路": 442,
  "中国石油三桥加油站(黔城美景东南)": 464,
  "SOHO": 521,
  "黄花街": 1501,
  "世纪窗文化传媒": 508,
  "蔡关社区卫生服务站新冠疫苗接种点": 488,
  "盛世旅社": 620,
  "老贵工瞿姐家常菜(花果园S区3区店)": 553,
  "金竹路": 771,
  "花海拾贝": 2119,
  "下坝": 1478,
  "农业农村部贵州小黑麦原种基地": 416,
  "油料研究所": 436,
  "云上之星幼儿园": 526,
  "农科院附属中学校园警务室": 1017,
  "金山村村委会": 553,
  "金家山": 587,
  "G60沪昆高速": 630,
  "贵阳阿哈湖国家湿地公园": 442,
  "平寨大桥": 454,
  "平寨": 546,
  "九龙亭(九龙茶峰)": 739,
  "雪厂": 453,
  "127县道": 637,
  "新雪公路": 412,
  "久安乡九龙山万亩茶园": 782,
  "犀牛坡": 551,
  "老窝寨": 449,
  "二毛烟酒店": 444
}