{
  "up": {
    "1": "圣仕非舟幼儿园",
    "2": "贵遵路",
    "3": "中国石油三桥加油站(黔城美景东南)",
    "4": "SOHO",
    "5": "黄花街",
    "6": "世纪窗文化传媒",
    "7": "蔡关社区卫生服务站新冠疫苗接种点",
    "8": "盛世旅社",
    "9": "老贵工瞿姐家常菜(花果园S区3区店)",
    "10": "金竹路",
    "11": "花海拾贝",
    "12": "下坝",
    "13": "农业农村部贵州小黑麦原种基地",
    "14": "油料研究所",
    "15": "云上之星幼儿园",
    "16": "农科院附属中学校园警务室",
    "17": "金山村村委会",
    "18": "金家山",
    "19": "G60沪昆高速",
    "20": "贵阳阿哈湖国家湿地公园",
    "21": "平寨大桥",
    "22": "平寨",
    "23": "九龙亭(九龙茶峰)",
    "24": "雪厂",
    "25": "127县道",
    "26": "新雪公路",
    "27": "久安乡九龙山万亩茶园",
    "28": "犀牛坡",
    "29": "老窝寨",
    "30": "二毛烟酒店",
    "31": "贵州农科帮富药材种苗育苗基地"
  },
  "down": {
    "32": "贵州农科帮富药材种苗育苗基地",
    "33": "二毛烟酒店",
    "34": "老窝寨",
    "35": "犀牛坡",
    "36": "久安乡九龙山万亩茶园",
    "37": "新雪公路",
    "38": "127县道",
    "39": "雪厂",
    "40": "九龙亭(九龙茶峰)",
    "41": "平寨",
    "42": "平寨大桥",
    "43": "贵阳阿哈湖国家湿地公园",
    "44": "G60沪昆高速",
    "45": "金家山",
    "46": "金山村村委会",
    "47": "农科院附属中学校园警务室",
    "48": "云上之星幼儿园",
    "49": "油料研究所",
    "50": "农业农村部贵州小黑麦原种基地",
    "51": "下坝",
    "52": "花海拾贝",
    "53": "金竹路",
    "54": "老贵工瞿姐家常菜(花果园S区3区店)",
    "55": "盛世旅社",
    "56": "蔡关社区卫生服务站新冠疫苗接种点",
    "57": "世纪窗文化传媒",
    "58": "黄花街",
    "59": "SOHO",
    "60": "中国石油三桥加油站(黔城美景东南)",
    "61": "贵遵路",
    "62": "圣仕非舟幼儿园"
  }
}