{
  "up": {
    "1": "观世音菩萨佛堂",
    "2": "方丈苑",
    "3": "贵安新区·金街",
    "4": "家电厨房设备(碧云山庄店)",
    "5": "黔灵山国际社区",
    "6": "黔春路(地铁站)",
    "7": "马哥清真餐馆(云阳佳苑店)",
    "8": "墨思教育",
    "9": "小车河路",
    "10": "界北关",
    "11": "合众七月螺蛳粉",
    "12": "贵州理工学院师生事物服务中心(3楼)",
    "13": "花果园S区2区",
    "14": "蝶泉亭",
    "15": "花果园运动中心",
    "16": "麦莎蒂斯烘焙甲秀南路店",
    "17": "农业科学院附属中学小学部",
    "18": "春晖苑小区",
    "19": "新苗幼儿园",
    "20": "徐哥带皮牛肉粉(烂泥沟分店)",
    "21": "天利集团繁荣楼",
    "22": "鸡心坡",
    "23": "誉将安全门",
    "24": "康打路",
    "25": "地利商务酒店",
    "26": "新艺家具厂",
    "27": "贵安路一期及联络线中心试验室",
    "28": "顶帝门窗贵阳分厂",
    "29": "摆顶",
    "30": "001县道",
    "31": "天河潭旅游度假区3号停车场",
    "32": "天河潭园艺山庄"
  },
  "down": {
    "33": "天河潭园艺山庄",
    "34": "天河潭旅游度假区3号停车场",
    "35": "001县道",
    "36": "摆顶",
    "37": "顶帝门窗贵阳分厂",
    "38": "贵安路一期及联络线中心试验室",
    "39": "新艺家具厂",
    "40": "地利商务酒店",
    "41": "康打路",
    "42": "誉将安全门",
    "43": "鸡心坡",
    "44": "天利集团繁荣楼",
    "45": "徐哥带皮牛肉粉(烂泥沟分店)",
    "46": "新苗幼儿园",
    "47": "春晖苑小区",
    "48": "农业科学院附属中学小学部",
    "49": "麦莎蒂斯烘焙甲秀南路店",
    "50": "花果园运动中心",
    "51": "蝶泉亭",
    "52": "花果园S区2区",
    "53": "贵州理工学院师生事物服务中心(3楼)",
    "54": "合众七月螺蛳粉",
    "55": "界北关",
    "56": "小车河路",
    "57": "墨思教育",
    "58": "马哥清真餐馆(云阳佳苑店)",
    "59": "黔春路(地铁站)",
    "60": "黔灵山国际社区",
    "61": "家电厨房设备(碧云山庄店)",
    "62": "贵安新区·金街",
    "63": "方丈苑",
    "64": "观世音菩萨佛堂"
  }
}