{
  "up": {
    "贵阳市云岩区雅关幼儿园(云璟分园)": 1,
    "宏业·康馨园": 2,
    "中国农业银行(三桥分理处)": 3,
    "三桥立交桥": 4,
    "烟火自助烧烤店": 5,
    "贵阳悦山博雅酒店": 6,
    "海马饭店(海马冲路)": 7,
    "谊康妇科": 8,
    "三姨娘爆炒三肠(威清路店)": 9,
    "绿茶餐厅(贵阳汇金星力城)": 10,
    "市西路商业街": 11,
    "中华会计网校(贵州分校)": 12,
    "人民大道": 13,
    "朝阳桥": 14,
    "松の肉来烧肉酒肆(兴隆社区店)": 15,
    "知家鱼火锅": 16,
    "长城花园(青年路)": 17,
    "油榨街": 18,
    "刘记烤全羊": 19,
    "贵州电网贵阳供电局双龙分局": 20,
    "二零六小区": 21,
    "首开·紫郡": 22,
    "鑫香醉鹅(首开·紫郡店)": 23,
    "南明区人民法院": 24,
    "贵阳市第一人民医院住院部": 25,
    "贵阳翼汇国际航空酒店": 26,
    "见龙洞路": 27,
    "万润·凌云台": 28,
    "山西机械化建设集团公司贵阳机场三期扩建飞行区项目部": 29,
    "210国道": 30
  },
  "down": {
    "210国道": 31,
    "山西机械化建设集团公司贵阳机场三期扩建飞行区项目部": 32,
    "万润·凌云台": 33,
    "见龙洞路": 34,
    "贵阳翼汇国际航空酒店": 35,
    "贵阳市第一人民医院住院部": 36,
    "南明区人民法院": 37,
    "鑫香醉鹅(首开·紫郡店)": 38,
    "首开·紫郡": 39,
    "二零六小区": 40,
    "贵州电网贵阳供电局双龙分局": 41,
    "刘记烤全羊": 42,
    "油榨街": 43,
    "长城花园(青年路)": 44,
    "知家鱼火锅": 45,
    "松の肉来烧肉酒肆(兴隆社区店)": 46,
    "朝阳桥": 47,
    "人民大道": 48,
    "中华会计网校(贵州分校)": 49,
    "市西路商业街": 50,
    "绿茶餐厅(贵阳汇金星力城)": 51,
    "三姨娘爆炒三肠(威清路店)": 52,
    "谊康妇科": 53,
    "海马饭店(海马冲路)": 54,
    "贵阳悦山博雅酒店": 55,
    "烟火自助烧烤店": 56,
    "三桥立交桥": 57,
    "中国农业银行(三桥分理处)": 58,
    "宏业·康馨园": 59,
    "贵阳市云岩区雅关幼儿园(云璟分园)": 60
  }
}