{
  "up": {
    "1": "贵阳北站花园酒店",
    "2": "火车北站隧道",
    "3": "会展城第二小学集团校",
    "4": "云岩富民村镇银行三桥支行",
    "5": "贵阳云岩馨悦烟酒店",
    "6": "中寨",
    "7": "亨特·萃山国际",
    "8": "圣泉社区分院",
    "9": "嘉亮眼镜",
    "10": "甘记罐罐鸡(数博万达店)",
    "11": "苗之道健康管理(集团)有限公司",
    "12": "恒大中央广场",
    "13": "方记小笼包(龙贤店)",
    "14": "蒋家肠旺面馆(龙瑞路店)",
    "15": "金阳南路",
    "16": "鱼米厢火锅家常菜(中铁逸都店)",
    "17": "贵州乌当农商银行野鸭支行",
    "18": "金龙路",
    "19": "博士府",
    "20": "宾阳大道",
    "21": "爱自心商务宾馆",
    "22": "金阳客车站(进站口)",
    "23": "白马山",
    "24": "金华雅美口腔",
    "25": "焕新墙布墙纸批发零售中心",
    "26": "林场",
    "27": "北京中农优品农业科技研究院贵州分院",
    "28": "锦湘楼(悦城店)",
    "29": "贵阳聚谊酒店",
    "30": "德国卡赫"
  },
  "down": {
    "31": "德国卡赫",
    "32": "贵阳聚谊酒店",
    "33": "锦湘楼(悦城店)",
    "34": "北京中农优品农业科技研究院贵州分院",
    "35": "林场",
    "36": "焕新墙布墙纸批发零售中心",
    "37": "金华雅美口腔",
    "38": "白马山",
    "39": "金阳客车站(进站口)",
    "40": "爱自心商务宾馆",
    "41": "宾阳大道",
    "42": "博士府",
    "43": "金龙路",
    "44": "贵州乌当农商银行野鸭支行",
    "45": "鱼米厢火锅家常菜(中铁逸都店)",
    "46": "金阳南路",
    "47": "蒋家肠旺面馆(龙瑞路店)",
    "48": "方记小笼包(龙贤店)",
    "49": "恒大中央广场",
    "50": "苗之道健康管理(集团)有限公司",
    "51": "甘记罐罐鸡(数博万达店)",
    "52": "嘉亮眼镜",
    "53": "圣泉社区分院",
    "54": "亨特·萃山国际",
    "55": "中寨",
    "56": "贵阳云岩馨悦烟酒店",
    "57": "云岩富民村镇银行三桥支行",
    "58": "会展城第二小学集团校",
    "59": "火车北站隧道",
    "60": "贵阳北站花园酒店"
  }
}