<?xml version="1.0" encoding="UTF-8"?>
<addition>
	<busStop id="529_0_00" name="三桥金山黑山羊肉粉" lane="-593486785_1" startPos="0.0" endPos="10.0" friendlyPos="True" lines="529" personCapacity="50"/>
	<busStop id="529_0_01" name="贵州众源星宝汽车服务有限公司" lane="-593486785_1" startPos="705.34" endPos="715.34" friendlyPos="True" lines="529" personCapacity="50"/>
	<busStop id="529_0_02" name="贵阳家园宾馆" lane="593486785_1" startPos="698.73" endPos="708.73" friendlyPos="True" lines="529" personCapacity="50"/>
	<busStop id="529_0_03" name="三桥农民新村" lane="-504937615#0_1" startPos="409.24" endPos="419.24" friendlyPos="True" lines="529" personCapacity="50"/>
	<busStop id="529_0_04" name="太阳能路灯" lane="504939367#1_1" startPos="103.77" endPos="113.77" friendlyPos="True" lines="529" personCapacity="50"/>
	<busStop id="529_0_05" name="圣泉酒店(三桥店)" lane="609521466#1_1" startPos="355.92" endPos="365.92" friendlyPos="True" lines="529" personCapacity="50"/>
	<busStop id="529_0_06" name="维维聚香阁(檀溪谷店)" lane="609521466#2_1" startPos="511.20000000000005" endPos="521.2" friendlyPos="True" lines="529" personCapacity="50"/>
	<busStop id="529_0_07" name="介白山庄" lane="505047009_1" startPos="1311.78" endPos="1321.78" friendlyPos="True" lines="529" personCapacity="50"/>
	<busStop id="529_0_08" name="蔡关路" lane="315753867#2_1" startPos="109.77" endPos="119.77" friendlyPos="True" lines="529" personCapacity="50"/>
	<busStop id="529_0_09" name="楷瑞酒店" lane="315753867#4_1" startPos="358.75" endPos="368.75" friendlyPos="True" lines="529" personCapacity="50"/>
	<busStop id="529_0_10" name="在水一方秘境" lane="200886891_1" startPos="610.4" endPos="620.4" friendlyPos="True" lines="529" personCapacity="50"/>
	<busStop id="529_0_11" name="花果园运动中心" lane="200886892_1" startPos="229.45" endPos="239.45" friendlyPos="True" lines="529" personCapacity="50"/>
	<busStop id="529_0_12" name="小车河大桥" lane="200886893_1" startPos="503.09000000000003" endPos="513.09" friendlyPos="True" lines="529" personCapacity="50"/>
	<busStop id="529_0_13" name="上坝" lane="200886889#0_1" startPos="2109.46" endPos="2119.46" friendlyPos="True" lines="529" personCapacity="50"/>
	<busStop id="529_0_14" name="贵州茶博园科技开发有限公司" lane="200886889#2_1" startPos="1187.28" endPos="1197.28" friendlyPos="True" lines="529" personCapacity="50"/>
	<busStop id="529_0_15" name="贵州省旱粮研究所" lane="824309278#0_1" startPos="100.92" endPos="110.92" friendlyPos="True" lines="529" personCapacity="50"/>
	<busStop id="529_0_16" name="川竹私厨·蜀南人家酒楼(农科院店)" lane="540239987#0_1" startPos="125.32" endPos="135.32" friendlyPos="True" lines="529" personCapacity="50"/>
	<busStop id="529_0_17" name="如意餐厅" lane="690890028#1_1" startPos="1061.14" endPos="1071.14" friendlyPos="True" lines="529" personCapacity="50"/>
	<busStop id="529_0_18" name="都勇明装饰工程有限公司" lane="503417588_1" startPos="2217.42" endPos="2227.42" friendlyPos="True" lines="529" personCapacity="50"/>
	<busStop id="529_0_19" name="铺天盖地井盖批发部" lane="593434689_1" startPos="846.17" endPos="856.17" friendlyPos="True" lines="529" personCapacity="50"/>
	<busStop id="529_0_20" name="贵安大道辅路" lane="593434788_1" startPos="746.82" endPos="756.82" friendlyPos="True" lines="529" personCapacity="50"/>
	<busStop id="529_0_21" name="超众电子秤厂家直销" lane="593434809#0_1" startPos="956.45" endPos="966.45" friendlyPos="True" lines="529" personCapacity="50"/>
	<busStop id="529_0_22" name="高升塘" lane="593434723_1" startPos="217.83" endPos="227.83" friendlyPos="True" lines="529" personCapacity="50"/>
	<busStop id="529_0_23" name="小伍自采草莓园" lane="593434724#1_1" startPos="1145.27" endPos="1155.27" friendlyPos="True" lines="529" personCapacity="50"/>
	<busStop id="529_0_24" name="贵安大道" lane="593434724#3_1" startPos="820.7" endPos="830.7" friendlyPos="True" lines="529" personCapacity="50"/>
	<busStop id="529_0_25" name="一品鹅庄" lane="609720247_1" startPos="422.09" endPos="432.09" friendlyPos="True" lines="529" personCapacity="50"/>
	<busStop id="529_0_26" name="摆顶" lane="609720926#0_1" startPos="464.97" endPos="474.97" friendlyPos="True" lines="529" personCapacity="50"/>
	<busStop id="529_0_27" name="观清路" lane="609720942#1_1" startPos="237.51" endPos="247.51" friendlyPos="True" lines="529" personCapacity="50"/>
	<busStop id="529_0_28" name="湖磊路" lane="609720934#0_1" startPos="1336.19" endPos="1346.19" friendlyPos="True" lines="529" personCapacity="50"/>
	<busStop id="529_0_29" name="贵州盛润再生资源回收有限公司" lane="540240012#0_1" startPos="248.32999999999998" endPos="258.33" friendlyPos="True" lines="529" personCapacity="50"/>
	<busStop id="529_1_00" name="贵州盛润再生资源回收有限公司" lane="609720948_1" startPos="0.0" endPos="10.0" friendlyPos="True" lines="529" personCapacity="50"/>
	<busStop id="529_1_01" name="湖磊路" lane="609722104_1" startPos="200.51999999999998" endPos="210.51999999999998" friendlyPos="True" lines="529" personCapacity="50"/>
	<busStop id="529_1_02" name="观清路" lane="609722121_1" startPos="291.77" endPos="301.77" friendlyPos="True" lines="529" personCapacity="50"/>
	<busStop id="529_1_03" name="摆顶" lane="442977602#1_1" startPos="47.05000000000001" endPos="57.05000000000001" friendlyPos="True" lines="529" personCapacity="50"/>
	<busStop id="529_1_04" name="一品鹅庄" lane="442977350#5_1" startPos="42.48" endPos="52.48" friendlyPos="True" lines="529" personCapacity="50"/>
	<busStop id="529_1_05" name="贵安大道" lane="442977566_1" startPos="271.35" endPos="281.35" friendlyPos="True" lines="529" personCapacity="50"/>
	<busStop id="529_1_06" name="小伍自采草莓园" lane="540240007_1" startPos="1041.24" endPos="1051.24" friendlyPos="True" lines="529" personCapacity="50"/>
	<busStop id="529_1_07" name="高升塘" lane="609722115_1" startPos="236.43" endPos="246.43" friendlyPos="True" lines="529" personCapacity="50"/>
	<busStop id="529_1_08" name="超众电子秤厂家直销" lane="609722099#0_1" startPos="382.90999999999997" endPos="392.90999999999997" friendlyPos="True" lines="529" personCapacity="50"/>
	<busStop id="529_1_09" name="贵安大道辅路" lane="540240014#1_1" startPos="470.8800000000001" endPos="480.8800000000001" friendlyPos="True" lines="529" personCapacity="50"/>
	<busStop id="529_1_10" name="铺天盖地井盖批发部" lane="609720937#0_1" startPos="107.19" endPos="117.19" friendlyPos="True" lines="529" personCapacity="50"/>
	<busStop id="529_1_11" name="都勇明装饰工程有限公司" lane="609720924_1" startPos="19.180000000000007" endPos="29.180000000000007" friendlyPos="True" lines="529" personCapacity="50"/>
	<busStop id="529_1_12" name="如意餐厅" lane="609720245#2_1" startPos="1106.51" endPos="1116.51" friendlyPos="True" lines="529" personCapacity="50"/>
	<busStop id="529_1_13" name="川竹私厨·蜀南人家酒楼(农科院店)" lane="593434747_1" startPos="7.059999999999945" endPos="17.059999999999945" friendlyPos="True" lines="529" personCapacity="50"/>
	<busStop id="529_1_14" name="贵州省旱粮研究所" lane="593434744_1" startPos="0" endPos="10" friendlyPos="True" lines="529" personCapacity="50"/>
	<busStop id="529_1_15" name="贵州茶博园科技开发有限公司" lane="593434766_1" startPos="0" endPos="10" friendlyPos="True" lines="529" personCapacity="50"/>
	<busStop id="529_1_16" name="上坝" lane="593434837_1" startPos="1341.5900000000001" endPos="1351.5900000000001" friendlyPos="True" lines="529" personCapacity="50"/>
	<busStop id="529_1_17" name="小车河大桥" lane="475686338_1" startPos="441.0899999999999" endPos="451.0899999999999" friendlyPos="True" lines="529" personCapacity="50"/>
	<busStop id="529_1_18" name="花果园运动中心" lane="588160577_1" startPos="142.06" endPos="152.06" friendlyPos="True" lines="529" personCapacity="50"/>
	<busStop id="529_1_19" name="在水一方秘境" lane="824309276#1_1" startPos="651.74" endPos="661.74" friendlyPos="True" lines="529" personCapacity="50"/>
	<busStop id="529_1_20" name="楷瑞酒店" lane="824309276#2_1" startPos="0" endPos="10" friendlyPos="True" lines="529" personCapacity="50"/>
	<busStop id="529_1_21" name="蔡关路" lane="749300753_1" startPos="0" endPos="10" friendlyPos="True" lines="529" personCapacity="50"/>
	<busStop id="529_1_22" name="介白山庄" lane="824309283_1" startPos="0" endPos="10" friendlyPos="True" lines="529" personCapacity="50"/>
	<busStop id="529_1_23" name="维维聚香阁(檀溪谷店)" lane="200886886_1" startPos="240.39999999999998" endPos="250.39999999999998" friendlyPos="True" lines="529" personCapacity="50"/>
	<busStop id="529_1_24" name="圣泉酒店(三桥店)" lane="200886894#0_1" startPos="77.77999999999997" endPos="87.77999999999997" friendlyPos="True" lines="529" personCapacity="50"/>
	<busStop id="529_1_25" name="太阳能路灯" lane="315753865_1" startPos="42.44" endPos="52.44" friendlyPos="True" lines="529" personCapacity="50"/>
	<busStop id="529_1_26" name="三桥农民新村" lane="315753901#2_1" startPos="161.77999999999997" endPos="171.77999999999997" friendlyPos="True" lines="529" personCapacity="50"/>
	<busStop id="529_1_27" name="贵阳家园宾馆" lane="100463950#0_1" startPos="0" endPos="10" friendlyPos="True" lines="529" personCapacity="50"/>
	<busStop id="529_1_28" name="贵州众源星宝汽车服务有限公司" lane="100463941#3_1" startPos="138.97000000000003" endPos="148.97000000000003" friendlyPos="True" lines="529" personCapacity="50"/>
	<busStop id="529_1_29" name="三桥金山黑山羊肉粉" lane="100463941#5_1" startPos="41.34" endPos="51.34" friendlyPos="True" lines="529" personCapacity="50"/>
</addition>
