<?xml version="1.0" encoding="UTF-8"?>
<addition>
	<busStop id="733_0_00" name="贵州医科大学附属肿瘤医院放疗楼" lane="-542268205_1" startPos="0.0" endPos="10.0" friendlyPos="True" lines="733" personCapacity="50"/>
	<busStop id="733_0_01" name="中环路西段" lane="-542268205_1" startPos="427.8" endPos="437.8" friendlyPos="True" lines="733" personCapacity="50"/>
	<busStop id="733_0_02" name="贵州省计量测试院宿舍" lane="542268205_1" startPos="408.26" endPos="418.26" friendlyPos="True" lines="733" personCapacity="50"/>
	<busStop id="733_0_03" name="头桥派出所治安亭" lane="542268210#1_1" startPos="455.38" endPos="465.38" friendlyPos="True" lines="733" personCapacity="50"/>
	<busStop id="733_0_04" name="贵龙园北园" lane="824662330_1" startPos="137.72" endPos="147.72" friendlyPos="True" lines="733" personCapacity="50"/>
	<busStop id="733_0_05" name="绝味鸭脖(二桥店)" lane="505047025_1" startPos="375.26" endPos="385.26" friendlyPos="True" lines="733" personCapacity="50"/>
	<busStop id="733_0_06" name="铳PRO" lane="505047026#2_1" startPos="144.17" endPos="154.17" friendlyPos="True" lines="733" personCapacity="50"/>
	<busStop id="733_0_07" name="花果园半山小镇W1区13栋" lane="609509213_1" startPos="212.91" endPos="222.91" friendlyPos="True" lines="733" personCapacity="50"/>
	<busStop id="733_0_08" name="顾先生公寓(遵义中路分店)" lane="609509207_1" startPos="101.38" endPos="111.38" friendlyPos="True" lines="733" personCapacity="50"/>
	<busStop id="733_0_09" name="贵阳市公安局南明分局五里冲派出所" lane="609509197_1" startPos="94.92" endPos="104.92" friendlyPos="True" lines="733" personCapacity="50"/>
	<busStop id="733_0_10" name="新疆正宗烧烤店" lane="542459847_1" startPos="279.59" endPos="289.59" friendlyPos="True" lines="733" personCapacity="50"/>
	<busStop id="733_0_11" name="张记口口鲜餐馆(蔡家关店)" lane="315753867#1_1" startPos="250.29000000000002" endPos="260.29" friendlyPos="True" lines="733" personCapacity="50"/>
	<busStop id="733_0_12" name="泽味园" lane="315753867#4_1" startPos="358.75" endPos="368.75" friendlyPos="True" lines="733" personCapacity="50"/>
	<busStop id="733_0_13" name="甲秀南路" lane="200886891_1" startPos="610.4" endPos="620.4" friendlyPos="True" lines="733" personCapacity="50"/>
	<busStop id="733_0_14" name="贵阳阿哈湖国家湿地公园" lane="200886892_1" startPos="229.45" endPos="239.45" friendlyPos="True" lines="733" personCapacity="50"/>
	<busStop id="733_0_15" name="兰草坝" lane="200886893_1" startPos="503.09000000000003" endPos="513.09" friendlyPos="True" lines="733" personCapacity="50"/>
	<busStop id="733_0_16" name="新新世纪工程机械专业技术培训有限责任公司" lane="200886889#0_1" startPos="2109.46" endPos="2119.46" friendlyPos="True" lines="733" personCapacity="50"/>
	<busStop id="733_0_17" name="盘山路" lane="200886889#2_1" startPos="1187.28" endPos="1197.28" friendlyPos="True" lines="733" personCapacity="50"/>
	<busStop id="733_0_18" name="甲秀黔程茶博园山庄" lane="824309278#0_1" startPos="100.92" endPos="110.92" friendlyPos="True" lines="733" personCapacity="50"/>
	<busStop id="733_0_19" name="贵阳市林城苗苗小学" lane="540239987#0_1" startPos="125.32" endPos="135.32" friendlyPos="True" lines="733" personCapacity="50"/>
	<busStop id="733_0_20" name="随源液压机械有限公司" lane="690890028#1_1" startPos="1061.14" endPos="1071.14" friendlyPos="True" lines="733" personCapacity="50"/>
	<busStop id="733_0_21" name="都勇明装饰工程有限公司" lane="503417588_1" startPos="2217.42" endPos="2227.42" friendlyPos="True" lines="733" personCapacity="50"/>
	<busStop id="733_0_22" name="蔡冲矿星宇公司" lane="593434689_1" startPos="846.17" endPos="856.17" friendlyPos="True" lines="733" personCapacity="50"/>
	<busStop id="733_0_23" name="贵州富力门配装饰材料有限公司" lane="593434788_1" startPos="746.82" endPos="756.82" friendlyPos="True" lines="733" personCapacity="50"/>
	<busStop id="733_0_24" name="誉将安全门" lane="593434809#0_1" startPos="956.45" endPos="966.45" friendlyPos="True" lines="733" personCapacity="50"/>
	<busStop id="733_0_25" name="贵阳依倩宾馆" lane="593434723_1" startPos="217.83" endPos="227.83" friendlyPos="True" lines="733" personCapacity="50"/>
	<busStop id="733_0_26" name="石板镇(地铁站)" lane="593434724#1_1" startPos="1145.27" endPos="1155.27" friendlyPos="True" lines="733" personCapacity="50"/>
	<busStop id="733_0_27" name="优品驿站供应链有限公司" lane="540239996_1" startPos="471.49" endPos="481.49" friendlyPos="True" lines="733" personCapacity="50"/>
	<busStop id="733_0_28" name="龙治" lane="588157192_1" startPos="479.64" endPos="489.64" friendlyPos="True" lines="733" personCapacity="50"/>
	<busStop id="733_0_29" name="招呼站(公交站)" lane="588157193_1" startPos="872.42" endPos="882.42" friendlyPos="True" lines="733" personCapacity="50"/>
	<busStop id="733_0_30" name="产投高科创新孵化中心" lane="588157188#0_1" startPos="1660.53" endPos="1670.53" friendlyPos="True" lines="733" personCapacity="50"/>
	<busStop id="733_0_31" name="王陆坝" lane="588157188#2_1" startPos="186.98" endPos="196.98" friendlyPos="True" lines="733" personCapacity="50"/>
	<busStop id="733_0_32" name="贵州产投集团高科技术产业基地" lane="540240015#3_1" startPos="729.82" endPos="739.82" friendlyPos="True" lines="733" personCapacity="50"/>
	<busStop id="733_1_00" name="贵州产投集团高科技术产业基地" lane="-670784935#3_1" startPos="0.0" endPos="10.0" friendlyPos="True" lines="733" personCapacity="50"/>
	<busStop id="733_1_01" name="王陆坝" lane="609722432#2_1" startPos="351.43" endPos="361.43" friendlyPos="True" lines="733" personCapacity="50"/>
	<busStop id="733_1_02" name="产投高科创新孵化中心" lane="540239993#2_1" startPos="269.99" endPos="279.99" friendlyPos="True" lines="733" personCapacity="50"/>
	<busStop id="733_1_03" name="招呼站(公交站)" lane="540239993#3_1" startPos="1632.93" endPos="1642.93" friendlyPos="True" lines="733" personCapacity="50"/>
	<busStop id="733_1_04" name="龙治" lane="588157195_1" startPos="851.99" endPos="861.99" friendlyPos="True" lines="733" personCapacity="50"/>
	<busStop id="733_1_05" name="优品驿站供应链有限公司" lane="588157189_1" startPos="140.22" endPos="150.22" friendlyPos="True" lines="733" personCapacity="50"/>
	<busStop id="733_1_06" name="石板镇(地铁站)" lane="588157191_1" startPos="403.31" endPos="413.31" friendlyPos="True" lines="733" personCapacity="50"/>
	<busStop id="733_1_07" name="贵阳依倩宾馆" lane="609720245#2_1" startPos="1201.51" endPos="1211.51" friendlyPos="True" lines="733" personCapacity="50"/>
	<busStop id="733_1_08" name="誉将安全门" lane="593434693_1" startPos="205.7" endPos="215.7" friendlyPos="True" lines="733" personCapacity="50"/>
	<busStop id="733_1_09" name="贵州富力门配装饰材料有限公司" lane="593434823#1_1" startPos="738.74" endPos="748.74" friendlyPos="True" lines="733" personCapacity="50"/>
	<busStop id="733_1_10" name="蔡冲矿星宇公司" lane="593434747_1" startPos="538.06" endPos="548.06" friendlyPos="True" lines="733" personCapacity="50"/>
	<busStop id="733_1_11" name="都勇明装饰工程有限公司" lane="593434744_1" startPos="737.06" endPos="747.06" friendlyPos="True" lines="733" personCapacity="50"/>
	<busStop id="733_1_12" name="随源液压机械有限公司" lane="593434837_1" startPos="1963.5900000000001" endPos="1973.5900000000001" friendlyPos="True" lines="733" personCapacity="50"/>
	<busStop id="733_1_13" name="贵阳市林城苗苗小学" lane="475686338_1" startPos="88.08999999999992" endPos="98.08999999999992" friendlyPos="True" lines="733" personCapacity="50"/>
	<busStop id="733_1_14" name="甲秀黔程茶博园山庄" lane="588160577_1" startPos="0" endPos="10" friendlyPos="True" lines="733" personCapacity="50"/>
	<busStop id="733_1_15" name="盘山路" lane="824309276#1_1" startPos="0" endPos="10" friendlyPos="True" lines="733" personCapacity="50"/>
	<busStop id="733_1_16" name="新新世纪工程机械专业技术培训有限责任公司" lane="824309276#2_1" startPos="0" endPos="10" friendlyPos="True" lines="733" personCapacity="50"/>
	<busStop id="733_1_17" name="兰草坝" lane="749300753_1" startPos="0" endPos="10" friendlyPos="True" lines="733" personCapacity="50"/>
	<busStop id="733_1_18" name="贵阳阿哈湖国家湿地公园" lane="824309283_1" startPos="0" endPos="10" friendlyPos="True" lines="733" personCapacity="50"/>
	<busStop id="733_1_19" name="甲秀南路" lane="749300746_1" startPos="132.56" endPos="142.56" friendlyPos="True" lines="733" personCapacity="50"/>
	<busStop id="733_1_20" name="泽味园" lane="200886886_1" startPos="249.39999999999998" endPos="259.4" friendlyPos="True" lines="733" personCapacity="50"/>
	<busStop id="733_1_21" name="张记口口鲜餐馆(蔡家关店)" lane="200886887_1" startPos="535.62" endPos="545.62" friendlyPos="True" lines="733" personCapacity="50"/>
	<busStop id="733_1_22" name="新疆正宗烧烤店" lane="542459856#1_1" startPos="12.819999999999993" endPos="22.819999999999993" friendlyPos="True" lines="733" personCapacity="50"/>
	<busStop id="733_1_23" name="贵阳市公安局南明分局五里冲派出所" lane="749270084#5_1" startPos="34.129999999999995" endPos="44.129999999999995" friendlyPos="True" lines="733" personCapacity="50"/>
	<busStop id="733_1_24" name="顾先生公寓(遵义中路分店)" lane="696117651#1_1" startPos="7.779999999999973" endPos="17.779999999999973" friendlyPos="True" lines="733" personCapacity="50"/>
	<busStop id="733_1_25" name="花果园半山小镇W1区13栋" lane="505047027#1_1" startPos="166.53999999999996" endPos="176.53999999999996" friendlyPos="True" lines="733" personCapacity="50"/>
	<busStop id="733_1_26" name="铳PRO" lane="505047027#2_1" startPos="0" endPos="10" friendlyPos="True" lines="733" personCapacity="50"/>
	<busStop id="733_1_27" name="绝味鸭脖(二桥店)" lane="505047027#3_1" startPos="12.060000000000002" endPos="22.060000000000002" friendlyPos="True" lines="733" personCapacity="50"/>
	<busStop id="733_1_28" name="贵龙园北园" lane="505047027#6_1" startPos="131.43" endPos="141.43" friendlyPos="True" lines="733" personCapacity="50"/>
	<busStop id="733_1_29" name="头桥派出所治安亭" lane="99322675#2_1" startPos="125.9" endPos="135.9" friendlyPos="True" lines="733" personCapacity="50"/>
	<busStop id="733_1_30" name="贵州省计量测试院宿舍" lane="99289467_1" startPos="94.83000000000001" endPos="104.83000000000001" friendlyPos="True" lines="733" personCapacity="50"/>
	<busStop id="733_1_31" name="中环路西段" lane="99291530_1" startPos="18.78" endPos="28.78" friendlyPos="True" lines="733" personCapacity="50"/>
	<busStop id="733_1_32" name="贵州医科大学附属肿瘤医院放疗楼" lane="-542268210#1_1" startPos="52.77999999999997" endPos="62.77999999999997" friendlyPos="True" lines="733" personCapacity="50"/>
</addition>
