<?xml version="1.0" encoding="UTF-8"?>
<addition>
	<busStop id="684_0_00" name="德克士(金源店)" lane="-670968931#0_1" startPos="0.0" endPos="10.0" friendlyPos="True" lines="684" personCapacity="50"/>
	<busStop id="684_0_01" name="铁钎大拇指烤牛肉金阳店" lane="-262115022#5_1" startPos="188.94" endPos="198.94" friendlyPos="True" lines="684" personCapacity="50"/>
	<busStop id="684_0_02" name="贵阳鸿运公寓" lane="262115032#2_1" startPos="288.85" endPos="298.85" friendlyPos="True" lines="684" personCapacity="50"/>
	<busStop id="684_0_03" name="龙吉路" lane="1064429420#0_1" startPos="248.91000000000003" endPos="258.91" friendlyPos="True" lines="684" personCapacity="50"/>
	<busStop id="684_0_04" name="砂锅粉(世纪城店)" lane="167994417#1_1" startPos="393.37" endPos="403.37" friendlyPos="True" lines="684" personCapacity="50"/>
	<busStop id="684_0_05" name="水西牛肉粉(恒大店)" lane="167994492_1" startPos="297.18" endPos="307.18" friendlyPos="True" lines="684" personCapacity="50"/>
	<busStop id="684_0_06" name="贵阳市观山湖区第六中学" lane="167994424#0_1" startPos="425.12" endPos="435.12" friendlyPos="True" lines="684" personCapacity="50"/>
	<busStop id="684_0_07" name="知金教育(贵阳中心)" lane="167994424#3_1" startPos="548.01" endPos="558.01" friendlyPos="True" lines="684" personCapacity="50"/>
	<busStop id="684_0_08" name="颈肩腰腿理疗体验中心" lane="167994424#4_1" startPos="647.52" endPos="657.52" friendlyPos="True" lines="684" personCapacity="50"/>
	<busStop id="684_0_09" name="贵遵路" lane="609517173#14_1" startPos="494.05" endPos="504.05" friendlyPos="True" lines="684" personCapacity="50"/>
	<busStop id="684_0_10" name="谢勇五金批发" lane="99322661#2_1" startPos="142.59" endPos="152.59" friendlyPos="True" lines="684" personCapacity="50"/>
	<busStop id="684_0_11" name="佬来嗑(三桥综合批发市场店)" lane="99322642_1" startPos="120.41999999999999" endPos="130.42" friendlyPos="True" lines="684" personCapacity="50"/>
	<busStop id="684_0_12" name="公共卫生科预防保健科" lane="99322618#3_1" startPos="353.69" endPos="363.69" friendlyPos="True" lines="684" personCapacity="50"/>
	<busStop id="684_0_13" name="周哥余庆剔骨鸭剔骨鸡(二桥店)" lane="99322618#5_1" startPos="241.32" endPos="251.32" friendlyPos="True" lines="684" personCapacity="50"/>
	<busStop id="684_0_14" name="正宗水城羊肉粉(贵龙园店)" lane="99322675#0_1" startPos="438.5" endPos="448.5" friendlyPos="True" lines="684" personCapacity="50"/>
	<busStop id="684_0_15" name="竹园新居" lane="505047026#2_1" startPos="144.17" endPos="154.17" friendlyPos="True" lines="684" personCapacity="50"/>
	<busStop id="684_0_16" name="老地方特色无烟烤鱼(半山小镇)" lane="669565568_1" startPos="506.79999999999995" endPos="516.8" friendlyPos="True" lines="684" personCapacity="50"/>
	<busStop id="684_0_17" name="花果园第一社区卫生服务中心新冠疫苗接种点" lane="749396451#0_1" startPos="201.69" endPos="211.69" friendlyPos="True" lines="684" personCapacity="50"/>
	<busStop id="684_0_18" name="味千拉面(花果园购物中心店)" lane="593434702_1" startPos="366.39" endPos="376.39" friendlyPos="True" lines="684" personCapacity="50"/>
	<busStop id="684_0_19" name="火动力厨房(花果园店)" lane="625321697#2_1" startPos="154.37" endPos="164.37" friendlyPos="True" lines="684" personCapacity="50"/>
	<busStop id="684_0_20" name="贵阳天泰荔星酒店" lane="99204590#1_1" startPos="249.16000000000003" endPos="259.16" friendlyPos="True" lines="684" personCapacity="50"/>
	<busStop id="684_0_21" name="阁老寨" lane="749524202#2_1" startPos="160.91" endPos="170.91" friendlyPos="True" lines="684" personCapacity="50"/>
	<busStop id="684_0_22" name="小姐姐烙锅" lane="749524199_1" startPos="610.18" endPos="620.18" friendlyPos="True" lines="684" personCapacity="50"/>
	<busStop id="684_0_23" name="车水路" lane="823825834_1" startPos="503.40999999999997" endPos="513.41" friendlyPos="True" lines="684" personCapacity="50"/>
	<busStop id="684_0_24" name="何记原汤牛肉粉" lane="823825833_1" startPos="415.57" endPos="425.57" friendlyPos="True" lines="684" personCapacity="50"/>
	<busStop id="684_0_25" name="瀚林德苑" lane="671337205#0_1" startPos="474.63" endPos="484.63" friendlyPos="True" lines="684" personCapacity="50"/>
	<busStop id="684_0_26" name="谷丰粮油市场" lane="671337200#0_1" startPos="220.53" endPos="230.53" friendlyPos="True" lines="684" personCapacity="50"/>
	<busStop id="684_0_27" name="甘荫塘农贸市场" lane="671337200#3_1" startPos="276.12" endPos="286.12" friendlyPos="True" lines="684" personCapacity="50"/>
	<busStop id="684_0_28" name="上坝路" lane="823825842#0_1" startPos="190.06" endPos="200.06" friendlyPos="True" lines="684" personCapacity="50"/>
	<busStop id="684_0_29" name="贵阳市后巢中心幼儿园" lane="671337182#1_1" startPos="1217.67" endPos="1227.67" friendlyPos="True" lines="684" personCapacity="50"/>
	<busStop id="684_0_30" name="甘平路" lane="348332811#0_1" startPos="604.63" endPos="614.63" friendlyPos="True" lines="684" personCapacity="50"/>
	<busStop id="684_0_31" name="菊花洞居委会服务站" lane="-671337137#0_1" startPos="508.95000000000005" endPos="518.95" friendlyPos="True" lines="684" personCapacity="50"/>
	<busStop id="684_1_00" name="菊花洞居委会服务站" lane="348332811#1_1" startPos="0.0" endPos="10.0" friendlyPos="True" lines="684" personCapacity="50"/>
	<busStop id="684_1_01" name="甘平路" lane="609720238#0_1" startPos="15.860000000000014" endPos="25.860000000000014" friendlyPos="True" lines="684" personCapacity="50"/>
	<busStop id="684_1_02" name="贵阳市后巢中心幼儿园" lane="609720238#1_1" startPos="58.95999999999998" endPos="68.95999999999998" friendlyPos="True" lines="684" personCapacity="50"/>
	<busStop id="684_1_03" name="上坝路" lane="823825838#0_1" startPos="172.01" endPos="182.01" friendlyPos="True" lines="684" personCapacity="50"/>
	<busStop id="684_1_04" name="甘荫塘农贸市场" lane="823825838#1_1" startPos="502.16999999999996" endPos="512.17" friendlyPos="True" lines="684" personCapacity="50"/>
	<busStop id="684_1_05" name="谷丰粮油市场" lane="671337203_1" startPos="83.41" endPos="93.41" friendlyPos="True" lines="684" personCapacity="50"/>
	<busStop id="684_1_06" name="瀚林德苑" lane="823825836_1" startPos="41.120000000000005" endPos="51.120000000000005" friendlyPos="True" lines="684" personCapacity="50"/>
	<busStop id="684_1_07" name="何记原汤牛肉粉" lane="823825831_1" startPos="22.70999999999998" endPos="32.70999999999998" friendlyPos="True" lines="684" personCapacity="50"/>
	<busStop id="684_1_08" name="车水路" lane="823825832#0_1" startPos="0" endPos="10" friendlyPos="True" lines="684" personCapacity="50"/>
	<busStop id="684_1_09" name="小姐姐烙锅" lane="823825832#1_1" startPos="318.68" endPos="328.68" friendlyPos="True" lines="684" personCapacity="50"/>
	<busStop id="684_1_10" name="阁老寨" lane="749524186_1" startPos="242.55" endPos="252.55" friendlyPos="True" lines="684" personCapacity="50"/>
	<busStop id="684_1_11" name="贵阳天泰荔星酒店" lane="99204592_1" startPos="78.87" endPos="88.87" friendlyPos="True" lines="684" personCapacity="50"/>
	<busStop id="684_1_12" name="火动力厨房(花果园店)" lane="99204583_1" startPos="306.34" endPos="316.34" friendlyPos="True" lines="684" personCapacity="50"/>
	<busStop id="684_1_13" name="味千拉面(花果园购物中心店)" lane="609509181#1_1" startPos="115.0" endPos="125.0" friendlyPos="True" lines="684" personCapacity="50"/>
	<busStop id="684_1_14" name="花果园第一社区卫生服务中心新冠疫苗接种点" lane="609509182#0_1" startPos="108.63" endPos="118.63" friendlyPos="True" lines="684" personCapacity="50"/>
	<busStop id="684_1_15" name="老地方特色无烟烤鱼(半山小镇)" lane="609509182#1_1" startPos="0" endPos="10" friendlyPos="True" lines="684" personCapacity="50"/>
	<busStop id="684_1_16" name="竹园新居" lane="315753901#0_1" startPos="4.539999999999999" endPos="14.54" friendlyPos="True" lines="684" personCapacity="50"/>
	<busStop id="684_1_17" name="正宗水城羊肉粉(贵龙园店)" lane="315753901#2_1" startPos="115.77999999999997" endPos="125.77999999999997" friendlyPos="True" lines="684" personCapacity="50"/>
	<busStop id="684_1_18" name="周哥余庆剔骨鸭剔骨鸡(二桥店)" lane="315753901#3_1" startPos="0" endPos="10" friendlyPos="True" lines="684" personCapacity="50"/>
	<busStop id="684_1_19" name="公共卫生科预防保健科" lane="315753901#4_1" startPos="0" endPos="10" friendlyPos="True" lines="684" personCapacity="50"/>
	<busStop id="684_1_20" name="佬来嗑(三桥综合批发市场店)" lane="750752095#0_1" startPos="0" endPos="10" friendlyPos="True" lines="684" personCapacity="50"/>
	<busStop id="684_1_21" name="谢勇五金批发" lane="-459810940#1_1" startPos="0" endPos="10" friendlyPos="True" lines="684" personCapacity="50"/>
	<busStop id="684_1_22" name="贵遵路" lane="-459810940#0_1" startPos="0" endPos="10" friendlyPos="True" lines="684" personCapacity="50"/>
	<busStop id="684_1_23" name="颈肩腰腿理疗体验中心" lane="-351974455#1_1" startPos="390.76" endPos="400.76" friendlyPos="True" lines="684" personCapacity="50"/>
	<busStop id="684_1_24" name="知金教育(贵阳中心)" lane="671324056_1" startPos="79.37" endPos="89.37" friendlyPos="True" lines="684" personCapacity="50"/>
	<busStop id="684_1_25" name="贵阳市观山湖区第六中学" lane="220105643#0_1" startPos="405.78" endPos="415.78" friendlyPos="True" lines="684" personCapacity="50"/>
	<busStop id="684_1_26" name="水西牛肉粉(恒大店)" lane="220105643#1_1" startPos="18.73" endPos="28.73" friendlyPos="True" lines="684" personCapacity="50"/>
	<busStop id="684_1_27" name="砂锅粉(世纪城店)" lane="220105643#4_1" startPos="355.94" endPos="365.94" friendlyPos="True" lines="684" personCapacity="50"/>
	<busStop id="684_1_28" name="龙吉路" lane="220105643#6_1" startPos="183.83999999999997" endPos="193.83999999999997" friendlyPos="True" lines="684" personCapacity="50"/>
	<busStop id="684_1_29" name="贵阳鸿运公寓" lane="-1064429420#4_1" startPos="175.8" endPos="185.8" friendlyPos="True" lines="684" personCapacity="50"/>
	<busStop id="684_1_30" name="铁钎大拇指烤牛肉金阳店" lane="-1064429420#0_1" startPos="240.64" endPos="250.64" friendlyPos="True" lines="684" personCapacity="50"/>
	<busStop id="684_1_31" name="德克士(金源店)" lane="262115029_1" startPos="17.27000000000001" endPos="27.27000000000001" friendlyPos="True" lines="684" personCapacity="50"/>
</addition>
