<?xml version="1.0" encoding="UTF-8"?>
<addition>
	<busStop id="903_0_00" name="能量医学" lane="167994415_1" startPos="0.0" endPos="10.0" friendlyPos="True" lines="903" personCapacity="50"/>
	<busStop id="903_0_01" name="星巴克(贵阳数博万达广场店)" lane="167994415_1" startPos="785.68" endPos="795.68" friendlyPos="True" lines="903" personCapacity="50"/>
	<busStop id="903_0_02" name="贵阳寻息阁酒店(贵阳北京西路世纪城店)" lane="167994455#0_1" startPos="437.17" endPos="447.17" friendlyPos="True" lines="903" personCapacity="50"/>
	<busStop id="903_0_03" name="长岭南路" lane="167994424#3_1" startPos="548.01" endPos="558.01" friendlyPos="True" lines="903" personCapacity="50"/>
	<busStop id="903_0_04" name="马王社区卫生服务中心新冠疫苗接种点" lane="167994424#4_1" startPos="647.52" endPos="657.52" friendlyPos="True" lines="903" personCapacity="50"/>
	<busStop id="903_0_05" name="贵阳市云岩区圣源学校" lane="167994398_1" startPos="473.23" endPos="483.23" friendlyPos="True" lines="903" personCapacity="50"/>
	<busStop id="903_0_06" name="乔氏台球俱乐部" lane="167994500#1_1" startPos="52.79" endPos="62.79" friendlyPos="True" lines="903" personCapacity="50"/>
	<busStop id="903_0_07" name="远俊三桥驾校" lane="167994522_1" startPos="448.69" endPos="458.69" friendlyPos="True" lines="903" personCapacity="50"/>
	<busStop id="903_0_08" name="黔灵湖滨苑" lane="167994519_1" startPos="409.81" endPos="419.81" friendlyPos="True" lines="903" personCapacity="50"/>
	<busStop id="903_0_09" name="贵州医科大学附属肿瘤医院第三住院楼" lane="167994425_1" startPos="415.38" endPos="425.38" friendlyPos="True" lines="903" personCapacity="50"/>
	<busStop id="903_0_10" name="贵阳市生态文明建设委员会(北新区路)" lane="99289488_1" startPos="239.02" endPos="249.02" friendlyPos="True" lines="903" personCapacity="50"/>
	<busStop id="903_0_11" name="贵州广播电视大学终身教育服务中心" lane="705369312_1" startPos="66.11" endPos="76.11" friendlyPos="True" lines="903" personCapacity="50"/>
	<busStop id="903_0_12" name="宾果英语" lane="749544687#2_1" startPos="136.01" endPos="146.01" friendlyPos="True" lines="903" personCapacity="50"/>
	<busStop id="903_0_13" name="贵阳银行(市北路支行)" lane="99289473#0_1" startPos="149.51" endPos="159.51" friendlyPos="True" lines="903" personCapacity="50"/>
	<busStop id="903_0_14" name="贵州医科大学-临床前药物研究所" lane="99289473#1_1" startPos="539.01" endPos="549.01" friendlyPos="True" lines="903" personCapacity="50"/>
	<busStop id="903_0_15" name="杨氏老凯里酸汤牛肉·干锅羊肉(梦想典城2期店)" lane="823899322#2_1" startPos="116.64" endPos="126.64" friendlyPos="True" lines="903" personCapacity="50"/>
	<busStop id="903_0_16" name="水城济佳羊肉粉" lane="81944501#1_1" startPos="181.29" endPos="191.29" friendlyPos="True" lines="903" personCapacity="50"/>
	<busStop id="903_0_17" name="贵州财经大学(鹿冲关校区)" lane="81944501#5_1" startPos="459.16" endPos="469.16" friendlyPos="True" lines="903" personCapacity="50"/>
	<busStop id="903_0_18" name="中天花园桃花园C座" lane="81944501#7_1" startPos="640.89" endPos="650.89" friendlyPos="True" lines="903" personCapacity="50"/>
	<busStop id="903_0_19" name="开智数学" lane="81944501#13_1" startPos="210.55" endPos="220.55" friendlyPos="True" lines="903" personCapacity="50"/>
	<busStop id="903_0_20" name="冯二毛黔厨(云岩万达广场店)" lane="1058249924#1_1" startPos="463.26" endPos="473.26" friendlyPos="True" lines="903" personCapacity="50"/>
	<busStop id="903_0_21" name="贵龙驾校" lane="1058249924#3_1" startPos="72.17" endPos="82.17" friendlyPos="True" lines="903" personCapacity="50"/>
	<busStop id="903_0_22" name="大坡路" lane="1058249924#5_1" startPos="542.94" endPos="552.94" friendlyPos="True" lines="903" personCapacity="50"/>
	<busStop id="903_0_23" name="赵家寨" lane="100481998#1_1" startPos="1890.18" endPos="1900.18" friendlyPos="True" lines="903" personCapacity="50"/>
	<busStop id="903_0_24" name="问枢堂养生馆" lane="101685872#0_1" startPos="793.21" endPos="803.21" friendlyPos="True" lines="903" personCapacity="50"/>
	<busStop id="903_0_25" name="金沙羊肉粉(保利香槟大道店)" lane="101685872#3_1" startPos="246.26" endPos="256.26" friendlyPos="True" lines="903" personCapacity="50"/>
	<busStop id="903_0_26" name="家具广场(幸福里东部新城1期店)" lane="101685873_1" startPos="306.93" endPos="316.93" friendlyPos="True" lines="903" personCapacity="50"/>
	<busStop id="903_0_27" name="贵州广物君豪别克钣喷中心" lane="101685878_1" startPos="903.9" endPos="913.9" friendlyPos="True" lines="903" personCapacity="50"/>
	<busStop id="903_0_28" name="贵州乾海聚航能源开发技术有限公司(航天路)" lane="101685847#0_1" startPos="596.95" endPos="606.95" friendlyPos="True" lines="903" personCapacity="50"/>
	<busStop id="903_0_29" name="迈达盛能源云开加油站" lane="101685842_1" startPos="257.41" endPos="267.41" friendlyPos="True" lines="903" personCapacity="50"/>
	<busStop id="903_1_00" name="迈达盛能源云开加油站" lane="101685835_1" startPos="0.0" endPos="10.0" friendlyPos="True" lines="903" personCapacity="50"/>
	<busStop id="903_1_01" name="贵州乾海聚航能源开发技术有限公司(航天路)" lane="101685839_1" startPos="94.79999999999995" endPos="104.79999999999995" friendlyPos="True" lines="903" personCapacity="50"/>
	<busStop id="903_1_02" name="贵州广物君豪别克钣喷中心" lane="101685871_1" startPos="257.61" endPos="267.61" friendlyPos="True" lines="903" personCapacity="50"/>
	<busStop id="903_1_03" name="家具广场(幸福里东部新城1期店)" lane="101685870_1" startPos="835.06" endPos="845.06" friendlyPos="True" lines="903" personCapacity="50"/>
	<busStop id="903_1_04" name="金沙羊肉粉(保利香槟大道店)" lane="101685853#0_1" startPos="86.94999999999999" endPos="96.94999999999999" friendlyPos="True" lines="903" personCapacity="50"/>
	<busStop id="903_1_05" name="问枢堂养生馆" lane="101685853#1_1" startPos="436.85" endPos="446.85" friendlyPos="True" lines="903" personCapacity="50"/>
	<busStop id="903_1_06" name="赵家寨" lane="101685853#3_1" startPos="707.03" endPos="717.03" friendlyPos="True" lines="903" personCapacity="50"/>
	<busStop id="903_1_07" name="大坡路" lane="101685859#2_1" startPos="83.12" endPos="93.12" friendlyPos="True" lines="903" personCapacity="50"/>
	<busStop id="903_1_08" name="贵龙驾校" lane="1058249922#3_1" startPos="420.30999999999995" endPos="430.30999999999995" friendlyPos="True" lines="903" personCapacity="50"/>
	<busStop id="903_1_09" name="冯二毛黔厨(云岩万达广场店)" lane="1058249922#5_1" startPos="143.23000000000002" endPos="153.23000000000002" friendlyPos="True" lines="903" personCapacity="50"/>
	<busStop id="903_1_10" name="开智数学" lane="1058249922#6_1" startPos="384.42" endPos="394.42" friendlyPos="True" lines="903" personCapacity="50"/>
	<busStop id="903_1_11" name="中天花园桃花园C座" lane="609465740#2_1" startPos="52.43000000000001" endPos="62.43000000000001" friendlyPos="True" lines="903" personCapacity="50"/>
	<busStop id="903_1_12" name="贵州财经大学(鹿冲关校区)" lane="609465740#5_1" startPos="29.310000000000002" endPos="39.31" friendlyPos="True" lines="903" personCapacity="50"/>
	<busStop id="903_1_13" name="水城济佳羊肉粉" lane="609465740#9_1" startPos="169.35" endPos="179.35" friendlyPos="True" lines="903" personCapacity="50"/>
	<busStop id="903_1_14" name="杨氏老凯里酸汤牛肉·干锅羊肉(梦想典城2期店)" lane="99317149#0_1" startPos="307.72" endPos="317.72" friendlyPos="True" lines="903" personCapacity="50"/>
	<busStop id="903_1_15" name="贵州医科大学-临床前药物研究所" lane="99317149#1_1" startPos="270.8900000000001" endPos="280.8900000000001" friendlyPos="True" lines="903" personCapacity="50"/>
	<busStop id="903_1_16" name="贵阳银行(市北路支行)" lane="99286376_1" startPos="0" endPos="10" friendlyPos="True" lines="903" personCapacity="50"/>
	<busStop id="903_1_17" name="宾果英语" lane="99289480#5_1" startPos="43.23000000000002" endPos="53.23000000000002" friendlyPos="True" lines="903" personCapacity="50"/>
	<busStop id="903_1_18" name="贵州广播电视大学终身教育服务中心" lane="99286373#1_1" startPos="0" endPos="10" friendlyPos="True" lines="903" personCapacity="50"/>
	<busStop id="903_1_19" name="贵阳市生态文明建设委员会(北新区路)" lane="99286373#2_1" startPos="261.87" endPos="271.87" friendlyPos="True" lines="903" personCapacity="50"/>
	<busStop id="903_1_20" name="贵州医科大学附属肿瘤医院第三住院楼" lane="99289474#5_1" startPos="17.5" endPos="27.5" friendlyPos="True" lines="903" personCapacity="50"/>
	<busStop id="903_1_21" name="黔灵湖滨苑" lane="99289476#1_1" startPos="213.72000000000003" endPos="223.72000000000003" friendlyPos="True" lines="903" personCapacity="50"/>
	<busStop id="903_1_22" name="远俊三桥驾校" lane="99291527#1_1" startPos="47.879999999999995" endPos="57.879999999999995" friendlyPos="True" lines="903" personCapacity="50"/>
	<busStop id="903_1_23" name="乔氏台球俱乐部" lane="99322643#2_1" startPos="125.14999999999998" endPos="135.14999999999998" friendlyPos="True" lines="903" personCapacity="50"/>
	<busStop id="903_1_24" name="贵阳市云岩区圣源学校" lane="99322643#3_1" startPos="7.409999999999997" endPos="17.409999999999997" friendlyPos="True" lines="903" personCapacity="50"/>
	<busStop id="903_1_25" name="马王社区卫生服务中心新冠疫苗接种点" lane="99322592#0_1" startPos="612.79" endPos="622.79" friendlyPos="True" lines="903" personCapacity="50"/>
	<busStop id="903_1_26" name="长岭南路" lane="99322592#3_1" startPos="108.32999999999998" endPos="118.32999999999998" friendlyPos="True" lines="903" personCapacity="50"/>
	<busStop id="903_1_27" name="贵阳寻息阁酒店(贵阳北京西路世纪城店)" lane="99322636#1_1" startPos="140.22" endPos="150.22" friendlyPos="True" lines="903" personCapacity="50"/>
	<busStop id="903_1_28" name="星巴克(贵阳数博万达广场店)" lane="-609517173#14_1" startPos="119.48000000000002" endPos="129.48000000000002" friendlyPos="True" lines="903" personCapacity="50"/>
	<busStop id="903_1_29" name="能量医学" lane="-609517173#10_1" startPos="37.61" endPos="47.61" friendlyPos="True" lines="903" personCapacity="50"/>
</addition>
