<?xml version="1.0" encoding="UTF-8"?>
<addition>
	<busStop id="460_0_00" name="贵阳市公安消防支队黔灵山路中队" lane="1064429357#6_1" startPos="0.0" endPos="10.0" friendlyPos="True" lines="460" personCapacity="50"/>
	<busStop id="460_0_01" name="贵州顺泰文化传媒有限公司" lane="1064429357#7_1" startPos="867.09" endPos="877.09" friendlyPos="True" lines="460" personCapacity="50"/>
	<busStop id="460_0_02" name="云隐山居(俊发滨湖俊园店)" lane="1064429358#9_1" startPos="368.95" endPos="378.95" friendlyPos="True" lines="460" personCapacity="50"/>
	<busStop id="460_0_03" name="齐记小笼包(恒大滨河左岸店)" lane="1064429358#11_1" startPos="412.49" endPos="422.49" friendlyPos="True" lines="460" personCapacity="50"/>
	<busStop id="460_0_04" name="中国银行(观山湖支行)" lane="352255223#24_1" startPos="428.58" endPos="438.58" friendlyPos="True" lines="460" personCapacity="50"/>
	<busStop id="460_0_05" name="仁骨康国灸堂" lane="670965292#5_1" startPos="418.62" endPos="428.62" friendlyPos="True" lines="460" personCapacity="50"/>
	<busStop id="460_0_06" name="白龙洞路" lane="1064429349#1_1" startPos="281.02" endPos="291.02" friendlyPos="True" lines="460" personCapacity="50"/>
	<busStop id="460_0_07" name="贵州龙(金源店)" lane="167994411#4_1" startPos="389.12" endPos="399.12" friendlyPos="True" lines="460" personCapacity="50"/>
	<busStop id="460_0_08" name="羊小子水城羊肉粉(世纪城店)" lane="167994459#1_1" startPos="393.01" endPos="403.01" friendlyPos="True" lines="460" personCapacity="50"/>
	<busStop id="460_0_09" name="龙翔路" lane="167994459#5_1" startPos="195.36" endPos="205.36" friendlyPos="True" lines="460" personCapacity="50"/>
	<busStop id="460_0_10" name="中铁逸都国际G2组团" lane="823903432_1" startPos="590.29" endPos="600.29" friendlyPos="True" lines="460" personCapacity="50"/>
	<busStop id="460_0_11" name="贵州开放大学(新校区)" lane="823903427#0_1" startPos="649.84" endPos="659.84" friendlyPos="True" lines="460" personCapacity="50"/>
	<busStop id="460_0_12" name="仙客来食坊" lane="823903427#5_1" startPos="430.86" endPos="440.86" friendlyPos="True" lines="460" personCapacity="50"/>
	<busStop id="460_0_13" name="金龙路" lane="823903427#7_1" startPos="325.03" endPos="335.03" friendlyPos="True" lines="460" personCapacity="50"/>
	<busStop id="460_0_14" name="原汤羊肉粉" lane="385774340_1" startPos="251.07999999999998" endPos="261.08" friendlyPos="True" lines="460" personCapacity="50"/>
	<busStop id="460_0_15" name="博士府" lane="183172156_1" startPos="428.38" endPos="438.38" friendlyPos="True" lines="460" personCapacity="50"/>
	<busStop id="460_0_16" name="绝味鸭脖(贵阳高铁东站店)" lane="230718075#0_1" startPos="270.68" endPos="280.68" friendlyPos="True" lines="460" personCapacity="50"/>
	<busStop id="460_0_17" name="干井大桥" lane="183172135#0_1" startPos="97.81" endPos="107.81" friendlyPos="True" lines="460" personCapacity="50"/>
	<busStop id="460_0_18" name="中共何官村支部委员会" lane="183172135#2_1" startPos="88.48" endPos="98.48" friendlyPos="True" lines="460" personCapacity="50"/>
	<busStop id="460_0_19" name="灯草塘隧道" lane="183172133_1" startPos="283.45" endPos="293.45" friendlyPos="True" lines="460" personCapacity="50"/>
	<busStop id="460_0_20" name="菜鸟驿站(贵阳金华吉利宿舍店)" lane="183172129_1" startPos="715.71" endPos="725.71" friendlyPos="True" lines="460" personCapacity="50"/>
	<busStop id="460_0_21" name="贵州乐思教汽车工贸有限公司" lane="750753093_1" startPos="771.77" endPos="781.77" friendlyPos="True" lines="460" personCapacity="50"/>
	<busStop id="460_0_22" name="观清路" lane="230719986_1" startPos="441.19" endPos="451.19" friendlyPos="True" lines="460" personCapacity="50"/>
	<busStop id="460_0_23" name="温馨家园" lane="230719976_1" startPos="169.15" endPos="179.15" friendlyPos="True" lines="460" personCapacity="50"/>
	<busStop id="460_0_24" name="金华派出所蒿芝警务室" lane="230719979_1" startPos="214.32" endPos="224.32" friendlyPos="True" lines="460" personCapacity="50"/>
	<busStop id="460_0_25" name="蒿芝居委会" lane="230719960#0_1" startPos="402.93" endPos="412.93" friendlyPos="True" lines="460" personCapacity="50"/>
	<busStop id="460_0_26" name="贵州南方乳业股份有限公司" lane="230719960#1_1" startPos="530.38" endPos="540.38" friendlyPos="True" lines="460" personCapacity="50"/>
	<busStop id="460_0_27" name="下铺村党支部" lane="230719960#2_1" startPos="594.38" endPos="604.38" friendlyPos="True" lines="460" personCapacity="50"/>
	<busStop id="460_0_28" name="金宫(社会化)机动车登记服务站" lane="230719961_1" startPos="2435.29" endPos="2445.29" friendlyPos="True" lines="460" personCapacity="50"/>
	<busStop id="460_0_29" name="清镇市龙滩幼儿园家长学校" lane="215575124_1" startPos="270.79" endPos="280.79" friendlyPos="True" lines="460" personCapacity="50"/>
	<busStop id="460_0_30" name="中共伟宏社区委员会" lane="215575122#1_1" startPos="442.52" endPos="452.52" friendlyPos="True" lines="460" personCapacity="50"/>
	<busStop id="460_1_00" name="中共伟宏社区委员会" lane="588184189#0_1" startPos="0.0" endPos="10.0" friendlyPos="True" lines="460" personCapacity="50"/>
	<busStop id="460_1_01" name="清镇市龙滩幼儿园家长学校" lane="215575120_1" startPos="359.6" endPos="369.6" friendlyPos="True" lines="460" personCapacity="50"/>
	<busStop id="460_1_02" name="金宫(社会化)机动车登记服务站" lane="673660919_1" startPos="42.05000000000018" endPos="52.05000000000018" friendlyPos="True" lines="460" personCapacity="50"/>
	<busStop id="460_1_03" name="下铺村党支部" lane="230719982_1" startPos="211.14999999999998" endPos="221.14999999999998" friendlyPos="True" lines="460" personCapacity="50"/>
	<busStop id="460_1_04" name="贵州南方乳业股份有限公司" lane="230719959#0_1" startPos="449.94000000000005" endPos="459.94000000000005" friendlyPos="True" lines="460" personCapacity="50"/>
	<busStop id="460_1_05" name="蒿芝居委会" lane="230719959#1_1" startPos="227.39" endPos="237.39" friendlyPos="True" lines="460" personCapacity="50"/>
	<busStop id="460_1_06" name="金华派出所蒿芝警务室" lane="230719959#2_1" startPos="11.990000000000009" endPos="21.99000000000001" friendlyPos="True" lines="460" personCapacity="50"/>
	<busStop id="460_1_07" name="温馨家园" lane="230719974_1" startPos="41.81999999999999" endPos="51.81999999999999" friendlyPos="True" lines="460" personCapacity="50"/>
	<busStop id="460_1_08" name="观清路" lane="230719987_1" startPos="238.85000000000002" endPos="248.85000000000002" friendlyPos="True" lines="460" personCapacity="50"/>
	<busStop id="460_1_09" name="贵州乐思教汽车工贸有限公司" lane="230719984_1" startPos="224.04000000000002" endPos="234.04000000000002" friendlyPos="True" lines="460" personCapacity="50"/>
	<busStop id="460_1_10" name="菜鸟驿站(贵阳金华吉利宿舍店)" lane="230719958_1" startPos="517.01" endPos="527.01" friendlyPos="True" lines="460" personCapacity="50"/>
	<busStop id="460_1_11" name="灯草塘隧道" lane="948687000_1" startPos="17.0" endPos="27.0" friendlyPos="True" lines="460" personCapacity="50"/>
	<busStop id="460_1_12" name="中共何官村支部委员会" lane="948686999_1" startPos="547.82" endPos="557.82" friendlyPos="True" lines="460" personCapacity="50"/>
	<busStop id="460_1_13" name="干井大桥" lane="183172134_1" startPos="146.22000000000003" endPos="156.22000000000003" friendlyPos="True" lines="460" personCapacity="50"/>
	<busStop id="460_1_14" name="绝味鸭脖(贵阳高铁东站店)" lane="183172131_1" startPos="210.57999999999998" endPos="220.57999999999998" friendlyPos="True" lines="460" personCapacity="50"/>
	<busStop id="460_1_15" name="博士府" lane="183172136#0_1" startPos="234.26999999999998" endPos="244.26999999999998" friendlyPos="True" lines="460" personCapacity="50"/>
	<busStop id="460_1_16" name="原汤羊肉粉" lane="183172138#0_1" startPos="69.5" endPos="79.5" friendlyPos="True" lines="460" personCapacity="50"/>
	<busStop id="460_1_17" name="金龙路" lane="183172138#1_1" startPos="137.86" endPos="147.86" friendlyPos="True" lines="460" personCapacity="50"/>
	<busStop id="460_1_18" name="仙客来食坊" lane="230718072_1" startPos="219.64" endPos="229.64" friendlyPos="True" lines="460" personCapacity="50"/>
	<busStop id="460_1_19" name="贵州开放大学(新校区)" lane="477982692_1" startPos="270.72" endPos="280.72" friendlyPos="True" lines="460" personCapacity="50"/>
	<busStop id="460_1_20" name="中铁逸都国际G2组团" lane="385774306#3_1" startPos="372.17999999999995" endPos="382.17999999999995" friendlyPos="True" lines="460" personCapacity="50"/>
	<busStop id="460_1_21" name="龙翔路" lane="385774306#7_1" startPos="41.200000000000045" endPos="51.200000000000045" friendlyPos="True" lines="460" personCapacity="50"/>
	<busStop id="460_1_22" name="羊小子水城羊肉粉(世纪城店)" lane="385774306#8_1" startPos="0" endPos="10" friendlyPos="True" lines="460" personCapacity="50"/>
	<busStop id="460_1_23" name="贵州龙(金源店)" lane="823903434_1" startPos="4.580000000000041" endPos="14.580000000000041" friendlyPos="True" lines="460" personCapacity="50"/>
	<busStop id="460_1_24" name="白龙洞路" lane="823903430_1" startPos="0" endPos="10" friendlyPos="True" lines="460" personCapacity="50"/>
	<busStop id="460_1_25" name="仁骨康国灸堂" lane="823903429#0_1" startPos="0" endPos="10" friendlyPos="True" lines="460" personCapacity="50"/>
	<busStop id="460_1_26" name="中国银行(观山湖支行)" lane="823903429#3_1" startPos="391.73" endPos="401.73" friendlyPos="True" lines="460" personCapacity="50"/>
	<busStop id="460_1_27" name="齐记小笼包(恒大滨河左岸店)" lane="167994417#1_1" startPos="50.370000000000005" endPos="60.370000000000005" friendlyPos="True" lines="460" personCapacity="50"/>
	<busStop id="460_1_28" name="云隐山居(俊发滨湖俊园店)" lane="1064429347#1_1" startPos="240.43" endPos="250.43" friendlyPos="True" lines="460" personCapacity="50"/>
	<busStop id="460_1_29" name="贵州顺泰文化传媒有限公司" lane="670968935#1_1" startPos="371.26" endPos="381.26" friendlyPos="True" lines="460" personCapacity="50"/>
	<busStop id="460_1_30" name="贵阳市公安消防支队黔灵山路中队" lane="211701764#12_1" startPos="351.71" endPos="361.71" friendlyPos="True" lines="460" personCapacity="50"/>
</addition>
