<?xml version="1.0" encoding="UTF-8"?>
<addition>
	<busStop id="596_0_00" name="贵阳国际贸易中心" lane="505070801#0_1" startPos="0.0" endPos="10.0" friendlyPos="True" lines="596" personCapacity="50"/>
	<busStop id="596_0_01" name="有炼咖啡馆(花果园C区店)" lane="505070801#0_1" startPos="560.25" endPos="570.25" friendlyPos="True" lines="596" personCapacity="50"/>
	<busStop id="596_0_02" name="雨田珠宝(MOROKO真珠)线下体验店" lane="823825795#1_1" startPos="113.54" endPos="123.54" friendlyPos="True" lines="596" personCapacity="50"/>
	<busStop id="596_0_03" name="新发装饰城" lane="593434754#5_1" startPos="1097.89" endPos="1107.89" friendlyPos="True" lines="596" personCapacity="50"/>
	<busStop id="596_0_04" name="一烙锅(太慈桥店)" lane="749524202#4_1" startPos="255.17000000000002" endPos="265.17" friendlyPos="True" lines="596" personCapacity="50"/>
	<busStop id="596_0_05" name="贵阳藏火锅重庆老火锅(水岸天街店)" lane="749524199_1" startPos="610.18" endPos="620.18" friendlyPos="True" lines="596" personCapacity="50"/>
	<busStop id="596_0_06" name="中国铁建·国际城山锦苑(西门)" lane="823825834_1" startPos="503.40999999999997" endPos="513.41" friendlyPos="True" lines="596" personCapacity="50"/>
	<busStop id="596_0_07" name="白龙洞" lane="823825833_1" startPos="415.57" endPos="425.57" friendlyPos="True" lines="596" personCapacity="50"/>
	<busStop id="596_0_08" name="花溪大道中段辅路" lane="671337205#0_1" startPos="474.63" endPos="484.63" friendlyPos="True" lines="596" personCapacity="50"/>
	<busStop id="596_0_09" name="中国工商银行(甘荫塘支行)" lane="671337200#0_1" startPos="220.53" endPos="230.53" friendlyPos="True" lines="596" personCapacity="50"/>
	<busStop id="596_0_10" name="贵阳市南明区文晟小学" lane="671337200#3_1" startPos="276.12" endPos="286.12" friendlyPos="True" lines="596" personCapacity="50"/>
	<busStop id="596_0_11" name="诚景·尚城销售中心" lane="671337200#5_1" startPos="167.29" endPos="177.29" friendlyPos="True" lines="596" personCapacity="50"/>
	<busStop id="596_0_12" name="中国邮政储蓄银行(贵阳市甘荫塘支行)" lane="823825840#1_1" startPos="111.6" endPos="121.6" friendlyPos="True" lines="596" personCapacity="50"/>
	<busStop id="596_0_13" name="御璟怡庭别苑" lane="348332820#1_1" startPos="377.42" endPos="387.42" friendlyPos="True" lines="596" personCapacity="50"/>
	<busStop id="596_0_14" name="杨记高山羊肉粉馆" lane="-348332819#0_1" startPos="442.48" endPos="452.48" friendlyPos="True" lines="596" personCapacity="50"/>
	<busStop id="596_0_15" name="7天连锁酒店(贵阳花溪大道中曹司店)" lane="101726061_1" startPos="650.39" endPos="660.39" friendlyPos="True" lines="596" personCapacity="50"/>
	<busStop id="596_0_16" name="贵州省农业科学院现代农业发展研究所" lane="101726037_1" startPos="1176.05" endPos="1186.05" friendlyPos="True" lines="596" personCapacity="50"/>
	<busStop id="596_0_17" name="大方郭氏豆花饭" lane="540239987#0_1" startPos="125.32" endPos="135.32" friendlyPos="True" lines="596" personCapacity="50"/>
	<busStop id="596_0_18" name="贵阳市花溪区三合学校" lane="690890028#1_1" startPos="1061.14" endPos="1071.14" friendlyPos="True" lines="596" personCapacity="50"/>
	<busStop id="596_0_19" name="遵义虾子众味佳羊肉粉(众味佳歺饮连锁合朋店)" lane="503417588_1" startPos="2217.42" endPos="2227.42" friendlyPos="True" lines="596" personCapacity="50"/>
	<busStop id="596_0_20" name="花溪区石板镇蔡冲学校" lane="593434689_1" startPos="846.17" endPos="856.17" friendlyPos="True" lines="596" personCapacity="50"/>
	<busStop id="596_0_21" name="贵州千乡原电子商务有限公司" lane="593434788_1" startPos="746.82" endPos="756.82" friendlyPos="True" lines="596" personCapacity="50"/>
	<busStop id="596_0_22" name="营盘" lane="593434809#0_1" startPos="956.45" endPos="966.45" friendlyPos="True" lines="596" personCapacity="50"/>
	<busStop id="596_0_23" name="石板二村村委会" lane="593434723_1" startPos="217.83" endPos="227.83" friendlyPos="True" lines="596" personCapacity="50"/>
	<busStop id="596_0_24" name="贵阳市花溪区石板卫生院" lane="593434724#1_1" startPos="1145.27" endPos="1155.27" friendlyPos="True" lines="596" personCapacity="50"/>
	<busStop id="596_0_25" name="正群能量医学体验馆" lane="593434724#3_1" startPos="820.7" endPos="830.7" friendlyPos="True" lines="596" personCapacity="50"/>
	<busStop id="596_0_26" name="小姚生态草莓园" lane="609720247_1" startPos="422.09" endPos="432.09" friendlyPos="True" lines="596" personCapacity="50"/>
	<busStop id="596_0_27" name="格林森门窗有限公司" lane="609720926#0_1" startPos="464.97" endPos="474.97" friendlyPos="True" lines="596" personCapacity="50"/>
	<busStop id="596_0_28" name="云上天河酒店" lane="540240006#3_1" startPos="176.53" endPos="186.53" friendlyPos="True" lines="596" personCapacity="50"/>
	<busStop id="596_0_29" name="湖磊北路" lane="609720932#0_1" startPos="1366.94" endPos="1376.94" friendlyPos="True" lines="596" personCapacity="50"/>
	<busStop id="596_0_30" name="沪昆线" lane="609720932#3_1" startPos="292.58" endPos="302.58" friendlyPos="True" lines="596" personCapacity="50"/>
	<busStop id="596_1_00" name="沪昆线" lane="609720948_1" startPos="0.0" endPos="10.0" friendlyPos="True" lines="596" personCapacity="50"/>
	<busStop id="596_1_01" name="湖磊北路" lane="609722104_1" startPos="168.51999999999998" endPos="178.51999999999998" friendlyPos="True" lines="596" personCapacity="50"/>
	<busStop id="596_1_02" name="云上天河酒店" lane="609722121_1" startPos="327.77" endPos="337.77" friendlyPos="True" lines="596" personCapacity="50"/>
	<busStop id="596_1_03" name="格林森门窗有限公司" lane="442977602#1_1" startPos="65.05000000000001" endPos="75.05000000000001" friendlyPos="True" lines="596" personCapacity="50"/>
	<busStop id="596_1_04" name="小姚生态草莓园" lane="609722125#2_1" startPos="43.25" endPos="53.25" friendlyPos="True" lines="596" personCapacity="50"/>
	<busStop id="596_1_05" name="正群能量医学体验馆" lane="540240007_1" startPos="52.24000000000001" endPos="62.24000000000001" friendlyPos="True" lines="596" personCapacity="50"/>
	<busStop id="596_1_06" name="贵阳市花溪区石板卫生院" lane="609722123_1" startPos="89.75999999999999" endPos="99.75999999999999" friendlyPos="True" lines="596" personCapacity="50"/>
	<busStop id="596_1_07" name="石板二村村委会" lane="609722115_1" startPos="402.43" endPos="412.43" friendlyPos="True" lines="596" personCapacity="50"/>
	<busStop id="596_1_08" name="营盘" lane="609722099#0_1" startPos="585.91" endPos="595.91" friendlyPos="True" lines="596" personCapacity="50"/>
	<busStop id="596_1_09" name="贵州千乡原电子商务有限公司" lane="540240014#1_1" startPos="710.8800000000001" endPos="720.8800000000001" friendlyPos="True" lines="596" personCapacity="50"/>
	<busStop id="596_1_10" name="花溪区石板镇蔡冲学校" lane="609720937#1_1" startPos="163.83" endPos="173.83" friendlyPos="True" lines="596" personCapacity="50"/>
	<busStop id="596_1_11" name="遵义虾子众味佳羊肉粉(众味佳歺饮连锁合朋店)" lane="609720925_1" startPos="214.17000000000002" endPos="224.17000000000002" friendlyPos="True" lines="596" personCapacity="50"/>
	<busStop id="596_1_12" name="贵阳市花溪区三合学校" lane="593434693_1" startPos="65.69999999999999" endPos="75.69999999999999" friendlyPos="True" lines="596" personCapacity="50"/>
	<busStop id="596_1_13" name="大方郭氏豆花饭" lane="593434747_1" startPos="395.05999999999995" endPos="405.05999999999995" friendlyPos="True" lines="596" personCapacity="50"/>
	<busStop id="596_1_14" name="贵州省农业科学院现代农业发展研究所" lane="593434744_1" startPos="342.05999999999995" endPos="352.05999999999995" friendlyPos="True" lines="596" personCapacity="50"/>
	<busStop id="596_1_15" name="7天连锁酒店(贵阳花溪大道中曹司店)" lane="593434837_1" startPos="827.5900000000001" endPos="837.5900000000001" friendlyPos="True" lines="596" personCapacity="50"/>
	<busStop id="596_1_16" name="杨记高山羊肉粉馆" lane="540239986#0_1" startPos="0" endPos="10" friendlyPos="True" lines="596" personCapacity="50"/>
	<busStop id="596_1_17" name="御璟怡庭别苑" lane="475686338_1" startPos="0" endPos="10" friendlyPos="True" lines="596" personCapacity="50"/>
	<busStop id="596_1_18" name="中国邮政储蓄银行(贵阳市甘荫塘支行)" lane="588160577_1" startPos="0" endPos="10" friendlyPos="True" lines="596" personCapacity="50"/>
	<busStop id="596_1_19" name="诚景·尚城销售中心" lane="824309276#1_1" startPos="0" endPos="10" friendlyPos="True" lines="596" personCapacity="50"/>
	<busStop id="596_1_20" name="贵阳市南明区文晟小学" lane="824309276#2_1" startPos="0" endPos="10" friendlyPos="True" lines="596" personCapacity="50"/>
	<busStop id="596_1_21" name="中国工商银行(甘荫塘支行)" lane="749300753_1" startPos="0" endPos="10" friendlyPos="True" lines="596" personCapacity="50"/>
	<busStop id="596_1_22" name="花溪大道中段辅路" lane="824309283_1" startPos="0" endPos="10" friendlyPos="True" lines="596" personCapacity="50"/>
	<busStop id="596_1_23" name="白龙洞" lane="749300746_1" startPos="0" endPos="10" friendlyPos="True" lines="596" personCapacity="50"/>
	<busStop id="596_1_24" name="中国铁建·国际城山锦苑(西门)" lane="749300758_1" startPos="0" endPos="10" friendlyPos="True" lines="596" personCapacity="50"/>
	<busStop id="596_1_25" name="贵阳藏火锅重庆老火锅(水岸天街店)" lane="200886898_1" startPos="172.19" endPos="182.19" friendlyPos="True" lines="596" personCapacity="50"/>
	<busStop id="596_1_26" name="一烙锅(太慈桥店)" lane="200886887_1" startPos="529.62" endPos="539.62" friendlyPos="True" lines="596" personCapacity="50"/>
	<busStop id="596_1_27" name="新发装饰城" lane="542459846_1" startPos="12.569999999999993" endPos="22.569999999999993" friendlyPos="True" lines="596" personCapacity="50"/>
	<busStop id="596_1_28" name="雨田珠宝(MOROKO真珠)线下体验店" lane="609509179_1" startPos="56.19999999999999" endPos="66.19999999999999" friendlyPos="True" lines="596" personCapacity="50"/>
	<busStop id="596_1_29" name="有炼咖啡馆(花果园C区店)" lane="99204573#3_1" startPos="30.080000000000013" endPos="40.08000000000001" friendlyPos="True" lines="596" personCapacity="50"/>
	<busStop id="596_1_30" name="贵阳国际贸易中心" lane="823825849#1_1" startPos="75.49000000000001" endPos="85.49000000000001" friendlyPos="True" lines="596" personCapacity="50"/>
</addition>
