{
  "up": {
    "三桥农民新村": 1,
    "亨特萃山国际幼儿园": 2,
    "亨特·萃山国际": 3,
    "谭醉牛(中坝路店)": 4,
    "佳通轮胎(中坝立交店)": 5,
    "富力华庭": 6,
    "弘福寺-五观堂": 7,
    "黔灵山公园-曲尺亭": 8,
    "九龙浴佛": 9,
    "姐妹串串香烫菜(八鸽岩路)": 10,
    "八鸽岩路": 11,
    "贵顺成(市北路店)": 12,
    "玖澳宅学风尚居": 13,
    "青云路留一手烤鱼旗舰店": 14,
    "蜜雪冰城(财经大学城店)": 15,
    "黄山冲路35号院": 16,
    "翠墨雅轩": 17,
    "田田教育(中天校区)": 18,
    "北二环": 19,
    "绝味鸭脖(恒大雅苑店)": 20,
    "当代贵州期刊传媒集团": 21,
    "乌当区人民法院审判法院": 22,
    "水锦花都2期": 23,
    "杭州小笼包(悦景新城店)": 24,
    "惠诚滋知(新添四店)": 25,
    "北龙路": 26,
    "周记新泰黑山羊火锅(新添寨)": 27,
    "翔宇物流": 28,
    "云锦庄": 29,
    "贵州永华技工学校": 30,
    "新村村": 31
  },
  "down": {
    "新村村": 32,
    "贵州永华技工学校": 33,
    "云锦庄": 34,
    "翔宇物流": 35,
    "周记新泰黑山羊火锅(新添寨)": 36,
    "北龙路": 37,
    "惠诚滋知(新添四店)": 38,
    "杭州小笼包(悦景新城店)": 39,
    "水锦花都2期": 40,
    "乌当区人民法院审判法院": 41,
    "当代贵州期刊传媒集团": 42,
    "绝味鸭脖(恒大雅苑店)": 43,
    "北二环": 44,
    "田田教育(中天校区)": 45,
    "翠墨雅轩": 46,
    "黄山冲路35号院": 47,
    "蜜雪冰城(财经大学城店)": 48,
    "青云路留一手烤鱼旗舰店": 49,
    "玖澳宅学风尚居": 50,
    "贵顺成(市北路店)": 51,
    "八鸽岩路": 52,
    "姐妹串串香烫菜(八鸽岩路)": 53,
    "九龙浴佛": 54,
    "黔灵山公园-曲尺亭": 55,
    "弘福寺-五观堂": 56,
    "富力华庭": 57,
    "佳通轮胎(中坝立交店)": 58,
    "谭醉牛(中坝路店)": 59,
    "亨特·萃山国际": 60,
    "亨特萃山国际幼儿园": 61,
    "三桥农民新村": 62
  }
}