{
  "融创·云湖十里": 1324,
  "兰花坡村": 3235,
  "中兴南友": 946,
  "布依人家": 724,
  "普洛斯贵阳铁路港物流园": 1820,
  "贵州胜鑫顺源汽车销售服务有限公司": 819,
  "尚品缘自助烧烤(装修中)": 533,
  "北京仙富癫痫病医学研究院清镇市分院": 585,
  "清镇恒坤酒店": 497,
  "智慧幼儿园": 517,
  "清镇出口(G60沪昆高速西向)": 2756,
  "贵州瑞达兴宏砖厂": 649,
  "G60沪昆高速": 585,
  "贵黄高速": 457,
  "广大城·耀晟一期": 461,
  "金华镇蒿芝村委会": 555,
  "蒿芝小学": 513,
  "贵州吉宏泰汽车零部件有限公司": 1200,
  "贵阳朗升汽车服务有限公司": 770,
  "观山湖区汽车配套产业园一期场平工程": 692,
  "金龙宾馆(新客车站店)": 473,
  "途眠宾馆": 532,
  "金阳客车站(进站口)": 467,
  "兴渝商务宾馆(新客车站店)": 675,
  "金华镇邮政储蓄银行": 565,
  "贵阳鑫翔五金锁具商行": 789,
  "白马山": 4595,
  "贵黄高速出口(东南向)": 1201,
  "派酒店(贵阳金关店)": 531
}