{
  "up": {
    "荷塘派出所水电九局社区警务室": 1,
    "大洼路": 2,
    "贵阳市云岩区书锦中学": 3,
    "聚福园": 4,
    "贵州省干细胞与组织工程技术研究中心": 5,
    "瑞幸咖啡(友山基金大厦店)": 6,
    "味清欢团餐运营中心(天一国际广场店)": 7,
    "中国工商银行(黔灵山路支行)": 8,
    "龙锦路": 9,
    "蜀国火锅冒菜": 10,
    "苏记胖子酱爆肉(金源街中店)": 11,
    "世纪花甲": 12,
    "贵阳露果酒店式公寓": 13,
    "广州路": 14,
    "兰州拉面(中铁·逸都国际店)": 15,
    "贵阳绿洲苑建材有限公司": 16,
    "观山湖区宾阳街道西南上城映山府": 17,
    "宾阳大道": 18,
    "佳味小厨": 19,
    "机动车尾气超标治理站": 20,
    "东旭宾馆(贵阳金阳新客车站店)": 21,
    "贵阳田甜宾馆": 22,
    "贵西能源金清加油站": 23,
    "吉利汽车贵阳制造基地": 24,
    "汽车电工": 25,
    "贵州泰歌凌机械化有限公司": 26,
    "金华派出所蒿芝村委会警务助理工作站": 27,
    "下铺源通驾校": 28,
    "北师大老教授协会实验幼儿园": 29,
    "G60沪昆高速": 30,
    "清镇市公安局交通警察大队车辆管理所": 31,
    "清镇市乐优童校外托管中心": 32,
    "贵黄高速": 33,
    "蓬来缘餐馆": 34
  },
  "down": {
    "蓬来缘餐馆": 35,
    "贵黄高速": 36,
    "清镇市乐优童校外托管中心": 37,
    "清镇市公安局交通警察大队车辆管理所": 38,
    "G60沪昆高速": 39,
    "北师大老教授协会实验幼儿园": 40,
    "下铺源通驾校": 41,
    "金华派出所蒿芝村委会警务助理工作站": 42,
    "贵州泰歌凌机械化有限公司": 43,
    "汽车电工": 44,
    "吉利汽车贵阳制造基地": 45,
    "贵西能源金清加油站": 46,
    "贵阳田甜宾馆": 47,
    "东旭宾馆(贵阳金阳新客车站店)": 48,
    "机动车尾气超标治理站": 49,
    "佳味小厨": 50,
    "宾阳大道": 51,
    "观山湖区宾阳街道西南上城映山府": 52,
    "贵阳绿洲苑建材有限公司": 53,
    "兰州拉面(中铁·逸都国际店)": 54,
    "广州路": 55,
    "贵阳露果酒店式公寓": 56,
    "世纪花甲": 57,
    "苏记胖子酱爆肉(金源街中店)": 58,
    "蜀国火锅冒菜": 59,
    "龙锦路": 60,
    "中国工商银行(黔灵山路支行)": 61,
    "味清欢团餐运营中心(天一国际广场店)": 62,
    "瑞幸咖啡(友山基金大厦店)": 63,
    "贵州省干细胞与组织工程技术研究中心": 64,
    "聚福园": 65,
    "贵阳市云岩区书锦中学": 66,
    "大洼路": 67,
    "荷塘派出所水电九局社区警务室": 68
  }
}