{
  "up": {
    "1": "黔灵山路",
    "2": "贵阳市云岩区未来之星幼儿园",
    "3": "美之都整形美容",
    "4": "苗家砂锅酸辣汤(天誉城店)",
    "5": "蛮坡立交",
    "6": "宅吉村综合楼",
    "7": "世纪园居委会",
    "8": "Miss龙英语家教补习",
    "9": "贵阳市城市综合执法支队云岩大队省府社区执法中队",
    "10": "贵医体检中心",
    "11": "巷子里老贵阳铁签烤牛肉(友谊路店)",
    "12": "蓝天宝贝艺术培训中心",
    "13": "养生氧疗馆",
    "14": "省人民医院(地铁站)",
    "15": "中国科学院地球化学研究所(观水路)",
    "16": "阳光100",
    "17": "冶金大院",
    "18": "南明区社区公园锦绣家园",
    "19": "贵钢地铁站C口",
    "20": "金牌王记牛肉粉(首钢贵州之光6号地块店)",
    "21": "6℃精酿啤酒馆(首钢贵州之光6号地块店)",
    "22": "谷立变",
    "23": "贵阳市森林公园",
    "24": "龙洞堡大道",
    "25": "时代假日酒店(贵阳龙洞堡机场店)",
    "26": "贵阳壹加陆酒店",
    "27": "瑞聚酒店(龙洞堡机场店)",
    "28": "新寨",
    "29": "贵州达兴宏建材",
    "30": "贵州贵泓洋汽修有限公司"
  },
  "down": {
    "31": "贵州贵泓洋汽修有限公司",
    "32": "贵州达兴宏建材",
    "33": "新寨",
    "34": "瑞聚酒店(龙洞堡机场店)",
    "35": "贵阳壹加陆酒店",
    "36": "时代假日酒店(贵阳龙洞堡机场店)",
    "37": "龙洞堡大道",
    "38": "贵阳市森林公园",
    "39": "谷立变",
    "40": "6℃精酿啤酒馆(首钢贵州之光6号地块店)",
    "41": "金牌王记牛肉粉(首钢贵州之光6号地块店)",
    "42": "贵钢地铁站C口",
    "43": "南明区社区公园锦绣家园",
    "44": "冶金大院",
    "45": "阳光100",
    "46": "中国科学院地球化学研究所(观水路)",
    "47": "省人民医院(地铁站)",
    "48": "养生氧疗馆",
    "49": "蓝天宝贝艺术培训中心",
    "50": "巷子里老贵阳铁签烤牛肉(友谊路店)",
    "51": "贵医体检中心",
    "52": "贵阳市城市综合执法支队云岩大队省府社区执法中队",
    "53": "Miss龙英语家教补习",
    "54": "世纪园居委会",
    "55": "宅吉村综合楼",
    "56": "蛮坡立交",
    "57": "苗家砂锅酸辣汤(天誉城店)",
    "58": "美之都整形美容",
    "59": "贵阳市云岩区未来之星幼儿园",
    "60": "黔灵山路"
  }
}