{
  "清坪路": 1786,
  "车之都科目二科目三考场": 785,
  "万山汽车修理厂": 499,
  "月半湾水疗酒店(清镇店)": 551,
  "贵黄高速": 463,
  "百马大道辅路": 483,
  "智慧幼儿园": 2722,
  "清镇市政务中心交通警察大队车管所满分教育学习室": 615,
  "佳兆业樾伴山": 551,
  "下铺村": 423,
  "全通驾校观山湖区二考场": 427,
  "云峰寺": 521,
  "贵州兴美盛园艺有限公司": 479,
  "石关路": 1166,
  "中共何官村支部委员会": 736,
  "黔吉酒店": 658,
  "摆岗坡": 439,
  "母享宾馆": 459,
  "金阳客车站": 516,
  "北京西路辅路": 466,
  "优居优住": 439,
  "肯德基(贵阳西南国际商贸城3号广场店)": 500,
  "贵阳高新龙泉纯净水厂": 840,
  "花溪牛肉粉(中铁·逸都国际店)": 1027,
  "逸峰": 611,
  "贵阳鸿福商务宾馆": 421,
  "遵义虾子羊肉粉(福州街店)": 770,
  "贵阳旅安居公寓": 822,
  "合肥路": 533,
  "湾河禅院": 458,
  "红星美凯龙全球家居生活广场MACALLINE(云岩店)": 1089,
  "广信双语幼儿园": 865,
  "贵阳云岩金阳小江汽修厂": 523
}