{
  "up": {
    "1": "贵安新区·金街",
    "2": "铁五局宿舍",
    "3": "中铁五局幼儿园",
    "4": "贵州龙(威清店)",
    "5": "徐鼎聚北京烤鸭",
    "6": "丽知苑餐饮",
    "7": "渔水湾时尚美食(贵乌路店)",
    "8": "平安小区(半边街)",
    "9": "特百惠(沙河专卖店)",
    "10": "清江阁",
    "11": "二关口",
    "12": "贵阳中天中学(花园校区)",
    "13": "宾隆超市(城市魔方店)",
    "14": "绝味鸭脖(恒大雅苑店)",
    "15": "奶漫清心(恒大雅苑店)",
    "16": "贵阳市公安局乌当分局",
    "17": "东二环",
    "18": "新竹路",
    "19": "智育星幼儿园",
    "20": "江之味片片鱼(幸福里东部新城1期店)",
    "21": "乌当振新社区幸福里卫生服务站",
    "22": "中国工商银行(新添支行)",
    "23": "新东温泉小镇",
    "24": "招呼站(公交站)",
    "25": "中国信合(洛湾分社)",
    "26": "贵州好山河",
    "27": "贵州远俊洛湾驾校(摩托车科二三考场)",
    "28": "中共三江社区支部委员会",
    "29": "正新轮胎(X132店)",
    "30": "小堰",
    "31": "文恋烟酒店",
    "32": "老场上"
  },
  "down": {
    "33": "老场上",
    "34": "文恋烟酒店",
    "35": "小堰",
    "36": "正新轮胎(X132店)",
    "37": "中共三江社区支部委员会",
    "38": "贵州远俊洛湾驾校(摩托车科二三考场)",
    "39": "贵州好山河",
    "40": "中国信合(洛湾分社)",
    "41": "招呼站(公交站)",
    "42": "新东温泉小镇",
    "43": "中国工商银行(新添支行)",
    "44": "乌当振新社区幸福里卫生服务站",
    "45": "江之味片片鱼(幸福里东部新城1期店)",
    "46": "智育星幼儿园",
    "47": "新竹路",
    "48": "东二环",
    "49": "贵阳市公安局乌当分局",
    "50": "奶漫清心(恒大雅苑店)",
    "51": "绝味鸭脖(恒大雅苑店)",
    "52": "宾隆超市(城市魔方店)",
    "53": "贵阳中天中学(花园校区)",
    "54": "二关口",
    "55": "清江阁",
    "56": "特百惠(沙河专卖店)",
    "57": "平安小区(半边街)",
    "58": "渔水湾时尚美食(贵乌路店)",
    "59": "丽知苑餐饮",
    "60": "徐鼎聚北京烤鸭",
    "61": "贵州龙(威清店)",
    "62": "中铁五局幼儿园",
    "63": "铁五局宿舍",
    "64": "贵安新区·金街"
  }
}